v/src/sha1_round.v
/**********************************************************
// Copyright 1891.06.02-2017.07.14
// Contact with 1098011272@qq.com
================ SHA1_round.v ======================
>> Author       : ZPN
>> Date         : 2022.09.26
>> Description  : SHA1 round function
  1、输入160 bits {ABCDE}，可以得到当前round的temp；
  2、输出160 bits {ABCDE}，移位变换后输出
>> note         : (1)To 
>>              : (2)My
>> V180121      : World.
************************************************************/
/* verilator lint_off UNSIGNED */
module sha1_round
    #(parameter N = 32)(
        input [159 : 0]  r_din    ,
        input [31  : 0]  w        ,
        input [7   : 0]  round    ,
//        input            valid_r  ,                  // round 有效信号
    
        output [159 : 0] r_dout     
//        output           ready_r                    // 80 轮加密结束后拉高
);

    //循环所用函数
    reg [N-1: 0] f;
    reg [N-1: 0] k;
    wire [N-1: 0] a_shift, b_shift, add_result;
    wire [N-1: 0] a = r_din[159: 128];
    wire [N-1: 0] b = r_din[127: 96 ];
    wire [N-1: 0] c = r_din[95 : 64 ];
    wire [N-1: 0] d = r_din[63 : 32 ];
    wire [N-1: 0] e = r_din[31 : 0 ];

    always@ (*) begin
        k = 32'd0;
        if((round >= 8'd0 ) && (round <= 8'd19)) k = 32'h5A82_7999;
        if((round >= 8'd20) && (round <= 8'd39)) k = 32'h6ED9_EBA1;
        if((round >= 8'd40) && (round <= 8'd59)) k = 32'h8F1B_BCDC;
        if((round >= 8'd60) && (round <= 8'd79)) k = 32'hCA62_C1D6;
    end

    always@ (*) begin
        f = 32'h0;
        if((round >= 8'd0 ) && (round <= 8'd19)) f = ((b & c) | (~b & d));
        if((round >= 8'd20) && (round <= 8'd39)) f = (b ^ c ^ d);
        if((round >= 8'd40) && (round <= 8'd59)) f = ((b & c) | (b & d) | (c & d));
        if((round >= 8'd60) && (round <= 8'd79)) f = (b ^ c ^ d);
    end

    assign a_shift = {a[26: 0], a[31:27]};
    assign b_shift = {b[1 : 0], b[31: 2]};
    assign add_result = (a_shift + ((f + k) + (e + w)));
    assign r_dout = {add_result, a, b_shift, c, d};

endmodule

v/src/sha1_w.v
/**********************************************************
// Copyright open source
// Contact with 1098011272@qq.com
================ sha1.v ======================
>> Author       : ZPN
>> Date         : 2022.09.26
>> Description  : SHA1 module that generates w
************************************************************/
/* verilator lint_off UNSIGNED */

module sha1_w
  #(parameter N = 32)(
    input          clk   ,
    input          rst_n ,
    input          valid_w ,
    input [7   :0] t     ,
    input [511 :0] din   ,

    output [N-1 :0] w    
);
  reg [511: 0] din_temp;
  wire [511: 0] din_temp_shift ;
//----------------------------------------------------------------
// The din_temp is 16*32 bits in size and can computes the next w.
  always @(posedge clk or negedge rst_n ) begin
    if(!rst_n) begin
      din_temp <= 512'h0 ;
    end else if((t == 8'd0) && valid_w) begin
      din_temp <= din    ;
    end else if((t >= 8'd1) && (t <= 8'd80)) begin
      din_temp <= din_temp_shift ;
    end else 
      din_temp <= 512'h0;
  end

//---------------------------------------------------------------
  wire [N-1 :0] w_gen_temp = din_temp[511: 480] ^ din_temp[447: 416] ^ din_temp[255: 224] ^ din_temp[95: 64];
  wire [N-1 :0] w_gen = {w_gen_temp[30: 0], w_gen_temp[31]};      // generate new w

// the first fifteen is din ,and next is w_gen
  assign din_temp_shift = ((t >= 8'd0) && (t <= 8'd16)) ? {din_temp[479: 0], din_temp[511: 480]} :
                          (t > 8'd16) && (t <= 8'd80)  ? {din_temp[479: 0], w_gen}              : 512'h0;

  assign w= ((t >= 8'd0) && (t <= 8'd16)) ? din_temp[511: 480] : w_gen;

endmodule

v/src/sha1_con.v
module sha1_con(
  input         clk     ,
  input         rst_n   ,
  input         valid   ,

  output [7 :0] t       ,
  output        ready_t
);

  parameter IDLE  = 2'b00;
  parameter ROUND = 2'b01;
  reg [7 :0] t_tem;
  reg [1 :0] s_cur, s_next;

  //-------------------------- First state machine -------------------------------
  always @(posedge clk or negedge rst_n) begin
    if(!rst_n) begin
      s_cur <= IDLE;
    end
    else begin
      s_cur <= s_next;
    end
  end

//-------------------------- Second state machine -------------------------------
  always @(*) begin
    case (s_cur)
      IDLE:begin
        if(valid) begin
          s_next = ROUND;
        end
        else s_next = IDLE;
      end

      ROUND: begin
        if(t < 8'h64) begin
          s_next = ROUND;
        end
        else begin
          s_next = IDLE;
        end
      end
      default: s_next = IDLE;
    endcase
  end

//-------------------------- Third state machine -------------------------------
  always @(posedge clk or negedge rst_n) begin
    if(!rst_n)
      t_tem <= 7'b0;
    else if(s_cur == ROUND) begin
      t_tem <= t_tem + 1'b1;
    end
    else t_tem <= 7'b0;
  end
  
//-------------------------------- Result --------------------------------------
  assign ready_t = ((s_cur == ROUND) && (t == 8'h63)) ;
  assign t = t_tem;
  
endmodule

v/src/sha1_top.v
/**********************************************************
// Copyright open source
// Contact with 1098011272@qq.com
================ sha1.v ======================
>> Author       : ZPN
>> Date         : 2022.09.29
>> Description  : SHA1 TOP module
************************************************************/

module sha1_top (
  input          clk   ,
  input          rst_n ,
  input          valid ,
  input [511: 0] din   ,

  output [159: 0] dout ,
  output          ready
);
  parameter H0 = 32'h6745_2301;
  parameter H1 = 32'hEFCD_AB89;
  parameter H2 = 32'h98BA_DCFE;
  parameter H3 = 32'h1032_5476;
  parameter H4 = 32'hC3D2_E1F0;

  wire [7 : 0] t;
  wire [31: 0] w_temp, a_temp, b_temp, c_temp, d_temp, e_temp;
  wire [159 : 0] r_din_temp;
  reg  [159 : 0] r_din;

always @(posedge clk or negedge rst_n) begin
  if(!rst_n) begin
    r_din <= 0;
  end else if(t == 8'd0) begin
    r_din <= {H0, H1, H2, H3, H4};
  end else if(t > 8'd0 && t < 8'd80) begin
    r_din <= r_din_temp;
  end else begin
    r_din <= 0;
  end
end

  sha1_con u_con (
    .clk   (clk  ),
    .rst_n (rst_n),
    .valid (valid),

    .t       (t     ),
    .ready_t (ready )
  );

  sha1_w u_w (
    .clk     (clk   ),
    .rst_n   (rst_n ),
    .valid_w (valid ),
    .t       (t     ),
    .din     (din   ),

    .w       (w_temp )
  );

  sha1_round u_round (
    .r_din (r_din  ),
    .w     (w_temp ),
    .round (t      ),

    .r_dout (r_din_temp)
  );
  assign a_temp = (t == 8'd80) ? (r_din_temp[159: 128] + H0): 32'd0;
  assign b_temp = (t == 8'd80) ? (r_din_temp[127: 96 ] + H1): 32'd0;
  assign c_temp = (t == 8'd80) ? (r_din_temp[95 : 64 ] + H2): 32'd0;
  assign d_temp = (t == 8'd80) ? (r_din_temp[63 : 32 ] + H3): 32'd0;
  assign e_temp = (t == 8'd80) ? (r_din_temp[31 : 0  ] + H4): 32'd0;

  assign dout = {a_temp, b_temp, c_temp, d_temp, e_temp};

endmodule

build/dump.vcd
$version Generated by VerilatedVcd $end
$date Thu Sep 29 15:07:17 2022 $end
$timescale 1ps $end

 $scope module TOP $end
  $var wire  1 a clk $end
  $var wire 512 d din [511:0] $end
  $var wire 160 t dout [159:0] $end
  $var wire  1 y ready $end
  $var wire  1 b rst_n $end
  $var wire  1 c valid $end
  $scope module sha1_top $end
   $var wire 32 { H0 [31:0] $end
   $var wire 32 | H1 [31:0] $end
   $var wire 32 } H2 [31:0] $end
   $var wire 32 ~ H3 [31:0] $end
   $var wire 32 !! H4 [31:0] $end
   $var wire 32 % a_temp [31:0] $end
   $var wire 32 & b_temp [31:0] $end
   $var wire 32 ' c_temp [31:0] $end
   $var wire  1 a clk $end
   $var wire 32 ( d_temp [31:0] $end
   $var wire 512 d din [511:0] $end
   $var wire 160 t dout [159:0] $end
   $var wire 32 ) e_temp [31:0] $end
   $var wire 160 / r_din [159:0] $end
   $var wire 160 * r_din_temp [159:0] $end
   $var wire  1 y ready $end
   $var wire  1 b rst_n $end
   $var wire  8 # t [7:0] $end
   $var wire  1 c valid $end
   $var wire 32 $ w_temp [31:0] $end
   $scope module u_con $end
    $var wire  2 "! IDLE [1:0] $end
    $var wire  2 #! ROUND [1:0] $end
    $var wire  1 a clk $end
    $var wire  1 y ready_t $end
    $var wire  1 b rst_n $end
    $var wire  2 4 s_cur [1:0] $end
    $var wire  2 z s_next [1:0] $end
    $var wire  8 # t [7:0] $end
    $var wire  8 # t_tem [7:0] $end
    $var wire  1 c valid $end
   $upscope $end
   $scope module u_round $end
    $var wire 32 $! N [31:0] $end
    $var wire 32 \ a [31:0] $end
    $var wire 32 Y a_shift [31:0] $end
    $var wire 32 [ add_result [31:0] $end
    $var wire 32 ] b [31:0] $end
    $var wire 32 Z b_shift [31:0] $end
    $var wire 32 ^ c [31:0] $end
    $var wire 32 _ d [31:0] $end
    $var wire 32 ` e [31:0] $end
    $var wire 32 W f [31:0] $end
    $var wire 32 X k [31:0] $end
    $var wire 160 / r_din [159:0] $end
    $var wire 160 * r_dout [159:0] $end
    $var wire  8 # round [7:0] $end
    $var wire 32 $ w [31:0] $end
   $upscope $end
   $scope module u_w $end
    $var wire 32 $! N [31:0] $end
    $var wire  1 a clk $end
    $var wire 512 d din [511:0] $end
    $var wire 512 5 din_temp [511:0] $end
    $var wire 512 E din_temp_shift [511:0] $end
    $var wire  1 b rst_n $end
    $var wire  8 # t [7:0] $end
    $var wire  1 c valid_w $end
    $var wire 32 $ w [31:0] $end
    $var wire 32 V w_gen [31:0] $end
    $var wire 32 U w_gen_temp [31:0] $end
   $upscope $end
  $upscope $end
 $upscope $end
$enddefinitions $end


#0
b00000000 #
b00000000000000000000000000000000 $
b00000000000000000000000000000000 %
b00000000000000000000000000000000 &
b00000000000000000000000000000000 '
b00000000000000000000000000000000 (
b00000000000000000000000000000000 )
b0000000000000000000000000000000000000000000000000000000000000000000000000000000000000000000000000000000000000000000000000000000000000000000000000000000000000000 *
b0000000000000000000000000000000000000000000000000000000000000000000000000000000000000000000000000000000000000000000000000000000000000000000000000000000000000000 /
b00 4
b00000000000000000000000000000000000000000000000000000000000000000000000000000000000000000000000000000000000000000000000000000000000000000000000000000000000000000000000000000000000000000000000000000000000000000000000000000000000000000000000000000000000000000000000000000000000000000000000000000000000000000000000000000000000000000000000000000000000000000000000000000000000000000000000000000000000000000000000000000000000000000000000000000000000000000000000000000000000000000000000000000000000000000000000000000000 5
b00000000000000000000000000000000000000000000000000000000000000000000000000000000000000000000000000000000000000000000000000000000000000000000000000000000000000000000000000000000000000000000000000000000000000000000000000000000000000000000000000000000000000000000000000000000000000000000000000000000000000000000000000000000000000000000000000000000000000000000000000000000000000000000000000000000000000000000000000000000000000000000000000000000000000000000000000000000000000000000000000000000000000000000000000000000 E
b00000000000000000000000000000000 U
b00000000000000000000000000000000 V
b00000000000000000000000000000000 W
b00000000000000000000000000000000 X
b00000000000000000000000000000000 Y
b00000000000000000000000000000000 Z
b00000000000000000000000000000000 [
b00000000000000000000000000000000 \
b00000000000000000000000000000000 ]
b00000000000000000000000000000000 ^
b00000000000000000000000000000000 _
b00000000000000000000000000000000 `
1a
0b
0c
b00000000000000000000000000000000000000000000000000000000000000000000000000000000000000000000000000000000000000000000000000000000000000000000000000000000000000000000000000000000000000000000000000000000000000000000000000000000000000000000000000000000000000000000000000000000000000000000000000000000000000000000000000000000000000000000000000000000000000000000000000000000000000000000000000000000000000000000000000000000000000000000000000000000000000000000000000000000000000000000000000000000000000000000000000000000 d
b0000000000000000000000000000000000000000000000000000000000000000000000000000000000000000000000000000000000000000000000000000000000000000000000000000000000000000 t
0y
b00 z
b01100111010001010010001100000001 {
b11101111110011011010101110001001 |
b10011000101110101101110011111110 }
b00010000001100100101010001110110 ~
b11000011110100101110000111110000 !!
b00 "!
b01 #!
b00000000000000000000000000100000 $!
#1
#2
#3
#4
#5
#6
#7
#8
#9
#10
0a
#11
#12
#13
#14
#15
#16
#17
#18
#19
#20
1a
#21
1b
#22
#23
#24
#25
#26
#27
#28
#29
#30
0a
#31
#32
#33
#34
#35
#36
#37
#38
#39
#40
b1010110001110111010000100001110001100111010001010010001100000001011110111111001101101010111000101001100010111010110111001111111000010000001100100101010001110110 *
b0110011101000101001000110000000111101111110011011010101110001001100110001011101011011100111111100001000000110010010101000111011011000011110100101110000111110000 /
b11101000101001000110000000101100 Y
b01111011111100110110101011100010 Z
b10101100011101110100001000011100 [
b01100111010001010010001100000001 \
b11101111110011011010101110001001 ]
b10011000101110101101110011111110 ^
b00010000001100100101010001110110 _
b11000011110100101110000111110000 `
1a
#41
#42
#43
#44
#45
#46
#47
#48
#49
#50
0a
#51
#52
#53
#54
#55
#56
#57
#58
#59
#60
b01100001011000100110001110000000 $
b0000110111011001101001011001110001100111010001010010001100000001011110111111001101101010111000101001100010111010110111001111111000010000001100100101010001110110 *
b01100001011000100110001110000000000000000000000000000000000000000000000000000000000000000000000000000000000000000000000000000000000000000000000000000000000000000000000000000000000000000000000000000000000000000000000000000000000000000000000000000000000000000000000000000000000000000000000000000000000000000000000000000000000000000000000000000000000000000000000000000000000000000000000000000000000000000000000000000000000000000000000000000000000000000000000000000000000000000000000000000000000000000000000000011000 5
b00000000000000000000000000000000000000000000000000000000000000000000000000000000000000000000000000000000000000000000000000000000000000000000000000000000000000000000000000000000000000000000000000000000000000000000000000000000000000000000000000000000000000000000000000000000000000000000000000000000000000000000000000000000000000000000000000000000000000000000000000000000000000000000000000000000000000000000000000000000000000000000000000000000000000000000000000000000000000000001100001100001011000100110001110000000 E
b01100001011000100110001110000000 U
b11000010110001001100011100000000 V
b00001101110110011010010110011100 [
1a
1c
b01100001011000100110001110000000000000000000000000000000000000000000000000000000000000000000000000000000000000000000000000000000000000000000000000000000000000000000000000000000000000000000000000000000000000000000000000000000000000000000000000000000000000000000000000000000000000000000000000000000000000000000000000000000000000000000000000000000000000000000000000000000000000000000000000000000000000000000000000000000000000000000000000000000000000000000000000000000000000000000000000000000000000000000000000011000 d
b01 z
#61
#62
#63
#64
#65
#66
#67
#68
#69
#70
0a
#71
#72
#73
#74
#75
#76
#77
#78
#79
#80
b01 4
1a
#81
#82
#83
#84
#85
#86
#87
#88
#89
#90
0a
#91
#92
#93
#94
#95
#96
#97
#98
#99
#100
b00000001 #
b0000000100010110111111000011001101100111010001010010001100000001011110111111001101101010111000101001100010111010110111001111111000010000001100100101010001110110 *
b10011000101110101101110011111110 W
b01011010100000100111100110011001 X
b00000001000101101111110000110011 [
1a
#101
#102
#103
#104
#105
#106
#107
#108
#109
#110
0a
#111
#112
#113
#114
#115
#116
#117
#118
#119
#120
b00000010 #
b00000000000000000000000000000000 $
b1000100110010000010100110110110100000001000101101111110000110011010110011101000101001000110000000111101111110011011010101110001010011000101110101101110011111110 *
b0000000100010110111111000011001101100111010001010010001100000001011110111111001101101010111000101001100010111010110111001111111000010000001100100101010001110110 /
b00000000000000000000000000000000000000000000000000000000000000000000000000000000000000000000000000000000000000000000000000000000000000000000000000000000000000000000000000000000000000000000000000000000000000000000000000000000000000000000000000000000000000000000000000000000000000000000000000000000000000000000000000000000000000000000000000000000000000000000000000000000000000000000000000000000000000000000000000000000000000000000000000000000000000000000000000000000000000000001100001100001011000100110001110000000 5
b00000000000000000000000000000000000000000000000000000000000000000000000000000000000000000000000000000000000000000000000000000000000000000000000000000000000000000000000000000000000000000000000000000000000000000000000000000000000000000000000000000000000000000000000000000000000000000000000000000000000000000000000000000000000000000000000000000000000000000000000000000000000000000000000000000000000000000000000000000000000000000000000000000000000110000110000101100010011000111000000000000000000000000000000000000000 E
b00000000000000000000000000000000 U
b00000000000000000000000000000000 V
b11111011111110111111111011111110 W
b00100010110111111000011001100000 Y
b01011001110100010100100011000000 Z
b10001001100100000101001101101101 [
b00000001000101101111110000110011 \
b01100111010001010010001100000001 ]
b01111011111100110110101011100010 ^
b10011000101110101101110011111110 _
b00010000001100100101010001110110 `
1a
#121
#122
#123
#124
#125
#126
#127
#128
#129
#130
0a
#131
#132
#133
#134
#135
#136
#137
#138
#139
#140
b00000011 #
b1010000100111001000011110000100010001001100100000101001101101101110000000100010110111111000011000101100111010001010010001100000001111011111100110110101011100010 *
b1000100110010000010100110110110100000001000101101111110000110011010110011101000101001000110000000111101111110011011010101110001010011000101110101101110011111110 /
b00000000000000000000000000000000000000000000000000000000000000000000000000000000000000000000000000000000000000000000000000000000000000000000000000000000000000000000000000000000000000000000000000000000000000000000000000000000000000000000000000000000000000000000000000000000000000000000000000000000000000000000000000000000000000000000000000000000000000000000000000000000000000000000000000000000000000000000000000000000000000000000000000000000000110000110000101100010011000111000000000000000000000000000000000000000 5
b00000000000000000000000000000000000000000000000000000000000000000000000000000000000000000000000000000000000000000000000000000000000000000000000000000000000000000000000000000000000000000000000000000000000000000000000000000000000000000000000000000000000000000000000000000000000000000000000000000000000000000000000000000000000000000000000000000000000000000000000000000000000000000000000000000000000000000000000000011000011000010110001001100011100000000000000000000000000000000000000000000000000000000000000000000000 E
b00000000000000000000000000011000 U
b00000000000000000000000000110000 V
b01111011111100010100101011000000 W
b00110010000010100110110110110001 Y
b11000000010001011011111100001100 Z
b10100001001110010000111100001000 [
b10001001100100000101001101101101 \
b00000001000101101111110000110011 ]
b01011001110100010100100011000000 ^
b01111011111100110110101011100010 _
b10011000101110101101110011111110 `
1a
#141
#142
#143
#144
#145
#146
#147
#148
#149
#150
0a
#151
#152
#153
#154
#155
#156
#157
#158
#159
#160
b00000100 #
b1100110111011000111000010001101110100001001110010000111100001000011000100110010000010100110110111100000001000101101111110000110001011001110100010100100011000000 *
b1010000100111001000011110000100010001001100100000101001101101101110000000100010110111111000011000101100111010001010010001100000001111011111100110110101011100010 /
b00000000000000000000000000000000000000000000000000000000000000000000000000000000000000000000000000000000000000000000000000000000000000000000000000000000000000000000000000000000000000000000000000000000000000000000000000000000000000000000000000000000000000000000000000000000000000000000000000000000000000000000000000000000000000000000000000000000000000000000000000000000000000000000000000000000000000000000000000011000011000010110001001100011100000000000000000000000000000000000000000000000000000000000000000000000 5
b00000000000000000000000000000000000000000000000000000000000000000000000000000000000000000000000000000000000000000000000000000000000000000000000000000000000000000000000000000000000000000000000000000000000000000000000000000000000000000000000000000000000000000000000000000000000000000000000000000000000000000000000000000000000000000000000000000000000000000000000000000000000000000001100001100001011000100110001110000000000000000000000000000000000000000000000000000000000000000000000000000000000000000000000000000000 E
b01100001011000100110001110000000 U
b11000010110001001100011100000000 V
b11010000010000010001101110001100 W
b00100111001000011110000100010100 Y
b01100010011001000001010011011011 Z
b11001101110110001110000100011011 [
b10100001001110010000111100001000 \
b10001001100100000101001101101101 ]
b11000000010001011011111100001100 ^
b01011001110100010100100011000000 _
b01111011111100110110101011100010 `
1a
#161
#162
#163
#164
#165
#166
#167
#168
#169
#170
0a
#171
#172
#173
#174
#175
#176
#177
#178
#179
#180
b00000101 #
b1100111111010100100110011101111011001101110110001110000100011011001010000100111001000011110000100110001001100100000101001101101111000000010001011011111100001100 *
b1100110111011000111000010001101110100001001110010000111100001000011000100110010000010100110110111100000001000101101111110000110001011001110100010100100011000000 /
b00000000000000000000000000000000000000000000000000000000000000000000000000000000000000000000000000000000000000000000000000000000000000000000000000000000000000000000000000000000000000000000000000000000000000000000000000000000000000000000000000000000000000000000000000000000000000000000000000000000000000000000000000000000000000000000000000000000000000000000000000000000000000000001100001100001011000100110001110000000000000000000000000000000000000000000000000000000000000000000000000000000000000000000000000000000 5
b00000000000000000000000000000000000000000000000000000000000000000000000000000000000000000000000000000000000000000000000000000000000000000000000000000000000000000000000000000000000000000000000000000000000000000000000000000000000000000000000000000000000000000000000000000000000000000000000000000000000000000000000000000000000000000000000000000000000110000110000101100010011000111000000000000000000000000000000000000000000000000000000000000000000000000000000000000000000000000000000000000000000000000000000000000000 E
b00000000000000000000000000000000 U
b00000000000000000000000000000000 V
b01100000011001001011010000001100 W
b10111011000111000010001101111001 Y
b00101000010011100100001111000010 Z
b11001111110101001001100111011110 [
b11001101110110001110000100011011 \
b10100001001110010000111100001000 ]
b01100010011001000001010011011011 ^
b11000000010001011011111100001100 _
b01011001110100010100100011000000 `
1a
#181
#182
#183
#184
#185
#186
#187
#188
#189
#190
0a
#191
#192
#193
#194
#195
#196
#197
#198
#199
#200
b00000110 #
b0011111111000111110010100100000011001111110101001001100111011110111100110111011000111000010001100010100001001110010000111100001001100010011001000001010011011011 *
b1100111111010100100110011101111011001101110110001110000100011011001010000100111001000011110000100110001001100100000101001101101111000000010001011011111100001100 /
b00000000000000000000000000000000000000000000000000000000000000000000000000000000000000000000000000000000000000000000000000000000000000000000000000000000000000000000000000000000000000000000000000000000000000000000000000000000000000000000000000000000000000000000000000000000000000000000000000000000000000000000000000000000000000000000000000000000000110000110000101100010011000111000000000000000000000000000000000000000000000000000000000000000000000000000000000000000000000000000000000000000000000000000000000000000 5
b00000000000000000000000000000000000000000000000000000000000000000000000000000000000000000000000000000000000000000000000000000000000000000000000000000000000000000000000000000000000000000000000000000000000000000000000000000000000000000000000000000000000000000000000000000000000000000000000000000000000000000000000000011000011000010110001001100011100000000000000000000000000000000000000000000000000000000000000000000000000000000000000000000000000000000000000000000000000000000000000000000000000000000000000000000000 E
b00101010011011000101010111000010 W
b11111010100100110011101111011001 Y
b11110011011101100011100001000110 Z
b00111111110001111100101001000000 [
b11001111110101001001100111011110 \
b11001101110110001110000100011011 ]
b00101000010011100100001111000010 ^
b01100010011001000001010011011011 _
b11000000010001011011111100001100 `
1a
#201
#202
#203
#204
#205
#206
#207
#208
#209
#210
0a
#211
#212
#213
#214
#215
#216
#217
#218
#219
#220
b00000111 #
b1001100100111110001100001100000100111111110001111100101001000000101100111111010100100110011101111111001101110110001110000100011000101000010011100100001111000010 *
b0011111111000111110010100100000011001111110101001001100111011110111100110111011000111000010001100010100001001110010000111100001001100010011001000001010011011011 /
b00000000000000000000000000000000000000000000000000000000000000000000000000000000000000000000000000000000000000000000000000000000000000000000000000000000000000000000000000000000000000000000000000000000000000000000000000000000000000000000000000000000000000000000000000000000000000000000000000000000000000000000000000011000011000010110001001100011100000000000000000000000000000000000000000000000000000000000000000000000000000000000000000000000000000000000000000000000000000000000000000000000000000000000000000000000 5
b00000000000000000000000000000000000000000000000000000000000000000000000000000000000000000000000000000000000000000000000000000000000000000000000000000000000000000000000000000000000000000000000000000000000000000000000000000000000000000000000000000000000000000000000000000000000000000001100001100001011000100110001110000000000000000000000000000000000000000000000000000000000000000000000000000000000000000000000000000000000000000000000000000000000000000000000000000000000000000000000000000000000000000000000000000000 E
b11100011010111100101101001000110 W
b11111000111110010100100000000111 Y
b10110011111101010010011001110111 Z
b10011001001111100011000011000001 [
b00111111110001111100101001000000 \
b11001111110101001001100111011110 ]
b11110011011101100011100001000110 ^
b00101000010011100100001111000010 _
b01100010011001000001010011011011 `
1a
#221
#222
#223
#224
#225
#226
#227
#228
#229
#230
0a
#231
#232
#233
#234
#235
#236
#237
#238
#239
#240
b00001000 #
b1001111010001100000001111101010010011001001111100011000011000001000011111111000111110010100100001011001111110101001001100111011111110011011101100011100001000110 *
b1001100100111110001100001100000100111111110001111100101001000000101100111111010100100110011101111111001101110110001110000100011000101000010011100100001111000010 /
b00000000000000000000000000000000000000000000000000000000000000000000000000000000000000000000000000000000000000000000000000000000000000000000000000000000000000000000000000000000000000000000000000000000000000000000000000000000000000000000000000000000000000000000000000000000000000000001100001100001011000100110001110000000000000000000000000000000000000000000000000000000000000000000000000000000000000000000000000000000000000000000000000000000000000000000000000000000000000000000000000000000000000000000000000000000 5
b00000000000000000000000000000000000000000000000000000000000000000000000000000000000000000000000000000000000000000000000000000000000000000000000000000000000000000000000000000000000000000000000000000000000000000000000000000000000000000000000000000000000110000110000101100010011000111000000000000000000000000000000000000000000000000000000000000000000000000000000000000000000000000000000000000000000000000000000000000000000000000000000000000000000000000000000000000000000000000000000000000000000000000000000000000000 E
b00000000000000000000000000011000 U
b00000000000000000000000000110000 V
b11110011111101010011001001000110 W
b00100111110001100001100000110011 Y
b00001111111100011111001010010000 Z
b10011110100011000000011111010100 [
b10011001001111100011000011000001 \
b00111111110001111100101001000000 ]
b10110011111101010010011001110111 ^
b11110011011101100011100001000110 _
b00101000010011100100001111000010 `
1a
#241
#242
#243
#244
#245
#246
#247
#248
#249
#250
0a
#251
#252
#253
#254
#255
#256
#257
#258
#259
#260
b00001001 #
b0100101101101010111000110010100010011110100011000000011111010100011001100100111110001100001100000000111111110001111100101001000010110011111101010010011001110111 *
b1001111010001100000001111101010010011001001111100011000011000001000011111111000111110010100100001011001111110101001001100111011111110011011101100011100001000110 /
b00000000000000000000000000000000000000000000000000000000000000000000000000000000000000000000000000000000000000000000000000000000000000000000000000000000000000000000000000000000000000000000000000000000000000000000000000000000000000000000000000000000000110000110000101100010011000111000000000000000000000000000000000000000000000000000000000000000000000000000000000000000000000000000000000000000000000000000000000000000000000000000000000000000000000000000000000000000000000000000000000000000000000000000000000000000 5
b00000000000000000000000000000000000000000000000000000000000000000000000000000000000000000000000000000000000000000000000000000000000000000000000000000000000000000000000000000000000000000000000000000000000000000000000000011000011000010110001001100011100000000000000000000000000000000000000000000000000000000000000000000000000000000000000000000000000000000000000000000000000000000000000000000000000000000000000000000000000000000000000000000000000000000000000000000000000000000000000000000000000000000000000000000000 E
b01100001011000100110001110000000 U
b11000010110001001100011100000000 V
b00101011111100010011011010110110 W
b11010001100000001111101010010011 Y
b01100110010011111000110000110000 Z
b01001011011010101110001100101000 [
b10011110100011000000011111010100 \
b10011001001111100011000011000001 ]
b00001111111100011111001010010000 ^
b10110011111101010010011001110111 _
b11110011011101100011100001000110 `
1a
#261
#262
#263
#264
#265
#266
#267
#268
#269
#270
0a
#271
#272
#273
#274
#275
#276
#277
#278
#279
#280
b00001010 #
b1000001101010001111110010010100101001011011010101110001100101000001001111010001100000001111101010110011001001111100011000011000000001111111100011111001010010000 *
b0100101101101010111000110010100010011110100011000000011111010100011001100100111110001100001100000000111111110001111100101001000010110011111101010010011001110111 /
b00000000000000000000000000000000000000000000000000000000000000000000000000000000000000000000000000000000000000000000000000000000000000000000000000000000000000000000000000000000000000000000000000000000000000000000000000011000011000010110001001100011100000000000000000000000000000000000000000000000000000000000000000000000000000000000000000000000000000000000000000000000000000000000000000000000000000000000000000000000000000000000000000000000000000000000000000000000000000000000000000000000000000000000000000000000 5
b00000000000000000000000000000000000000000000000000000000000000000000000000000000000000000000000000000000000000000000000000000000000000000000000000000000000000000000000000000000000000000001100001100001011000100110001110000000000000000000000000000000000000000000000000000000000000000000000000000000000000000000000000000000000000000000000000000000000000000000000000000000000000000000000000000000000000000000000000000000000000000000000000000000000000000000000000000000000000000000000000000000000000000000000000000000 E
b00000000000000000000000000000000 U
b00000000000000000000000000000000 V
b00000111011111011111010000010000 W
b01101101010111000110010100001001 Y
b00100111101000110000000111110101 Z
b10000011010100011111100100101001 [
b01001011011010101110001100101000 \
b10011110100011000000011111010100 ]
b01100110010011111000110000110000 ^
b00001111111100011111001010010000 _
b10110011111101010010011001110111 `
1a
#281
#282
#283
#284
#285
#286
#287
#288
#289
#290
0a
#291
#292
#293
#294
#295
#296
#297
#298
#299
#300
b00001011 #
b1111101111011010100111101000100110000011010100011111100100101001000100101101101010111000110010100010011110100011000000011111010101100110010011111000110000110000 *
b1000001101010001111110010010100101001011011010101110001100101000001001111010001100000001111101010110011001001111100011000011000000001111111100011111001010010000 /
b00000000000000000000000000000000000000000000000000000000000000000000000000000000000000000000000000000000000000000000000000000000000000000000000000000000000000000000000000000000000000000001100001100001011000100110001110000000000000000000000000000000000000000000000000000000000000000000000000000000000000000000000000000000000000000000000000000000000000000000000000000000000000000000000000000000000000000000000000000000000000000000000000000000000000000000000000000000000000000000000000000000000000000000000000000000 5
b00000000000000000000000000000000000000000000000000000000000000000000000000000000000000000000000000000000000000000000000000000000000000000000000000000000000110000110000101100010011000111000000000000000000000000000000000000000000000000000000000000000000000000000000000000000000000000000000000000000000000000000000000000000000000000000000000000000000000000000000000000000000000000000000000000000000000000000000000000000000000000000000000000000000000000000000000000000000000000000000000000000000000000000000000000000 E
b00100111001001110000110100110000 W
b01101010001111110010010100110000 Y
b00010010110110101011100011001010 Z
b11111011110110101001111010001001 [
b10000011010100011111100100101001 \
b01001011011010101110001100101000 ]
b00100111101000110000000111110101 ^
b01100110010011111000110000110000 _
b00001111111100011111001010010000 `
1a
#301
#302
#303
#304
#305
#306
#307
#308
#309
#310
0a
#311
#312
#313
#314
#315
#316
#317
#318
#319
#320
b00001100 #
b0110001100011000100011111110010011111011110110101001111010001001011000001101010001111110010010100001001011011010101110001100101000100111101000110000000111110101 *
b1111101111011010100111101000100110000011010100011111100100101001000100101101101010111000110010100010011110100011000000011111010101100110010011111000110000110000 /
b00000000000000000000000000000000000000000000000000000000000000000000000000000000000000000000000000000000000000000000000000000000000000000000000000000000000110000110000101100010011000111000000000000000000000000000000000000000000000000000000000000000000000000000000000000000000000000000000000000000000000000000000000000000000000000000000000000000000000000000000000000000000000000000000000000000000000000000000000000000000000000000000000000000000000000000000000000000000000000000000000000000000000000000000000000000 5
b00000000000000000000000000000000000000000000000000000000000000000000000000000000000000000000000000000000000000000000000000011000011000010110001001100011100000000000000000000000000000000000000000000000000000000000000000000000000000000000000000000000000000000000000000000000000000000000000000000000000000000000000000000000000000000000000000000000000000000000000000000000000000000000000000000000000000000000000000000000000000000000000000000000000000000000000000000000000000000000000000000000000000000000000000000000 E
b00100110111100101011100011011100 W
b01111011010100111101000100111111 Y
b01100000110101000111111001001010 Z
b01100011000110001000111111100100 [
b11111011110110101001111010001001 \
b10000011010100011111100100101001 ]
b00010010110110101011100011001010 ^
b00100111101000110000000111110101 _
b01100110010011111000110000110000 `
1a
#321
#322
#323
#324
#325
#326
#327
#328
#329
#330
0a
#331
#332
#333
#334
#335
#336
#337
#338
#339
