v/src/sha1_w.v
/**********************************************************
// Copyright open source
// Contact with 1098011272@qq.com
================ sha1.v ======================
>> Author       : ZPN
>> Date         : 2022.09.26
>> Description  : SHA1 module that generates w
************************************************************/
/* verilator lint_off UNSIGNED */

module sha1_w
  #(parameter N = 32)(
    input          clk   ,
    input          rst_n ,
    input          valid_w ,
    input [7   :0] t     ,
    input [511 :0] din   ,

    output [N-1 :0] w    ,
    output          ready_w 
);
  reg [511: 0] din_temp;
  wire [511: 0] din_temp_shift ;
//----------------------------------------------------------------
// The din_temp is 16*32 bits in size and can computes the next w.
  always @(posedge clk or negedge rst_n ) begin
    if(!rst_n) begin
      din_temp <= 512'h0 ;
    end else if((t == 8'd0) && valid_w) begin
      din_temp <= din    ;
    end else if((t > 8'd0) && (t <= 8'd79)) begin
      din_temp <= din_temp_shift ;
    end
  end

//---------------------------------------------------------------
  wire [N-1 :0] w_gen_temp = din_temp[511: 480] ^ din_temp[447: 416] ^ din_temp[255: 224] ^ din_temp[95: 64];
  wire [N-1 :0] w_gen = {w_gen_temp[30: 0], w_gen_temp[31]};      // generate new w

// the first fifteen is din ,and next is w_gen
  assign din_temp_shift = ((t >= 8'd0) && (t <= 8'd15)) ? {din_temp[479: 0], din_temp[511: 480]} :
                          (t >= 8'd16) && (t <= 8'd79)  ? {din_temp[479: 0], w_gen}              : 512'h0;

  assign w= ((t >= 8'd0) && (t <= 8'd15)) ? din_temp[511: 480] : w_gen;
  assign ready_w = (t == 8'd79);

endmodule

build/dump.vcd
$version Generated by VerilatedVcd $end
$date Thu Sep 29 09:11:44 2022 $end
$timescale 1ps $end

 $scope module TOP $end
  $var wire  1 5 clk $end
  $var wire 512 9 din [511:0] $end
  $var wire  1 J ready_w $end
  $var wire  1 6 rst_n $end
  $var wire  8 8 t [7:0] $end
  $var wire  1 7 valid_w $end
  $var wire 32 I w [31:0] $end
  $scope module sha1_w $end
   $var wire 32 [ N [31:0] $end
   $var wire  1 5 clk $end
   $var wire 512 9 din [511:0] $end
   $var wire 512 # din_temp [511:0] $end
   $var wire 512 K din_temp_shift [511:0] $end
   $var wire  1 J ready_w $end
   $var wire  1 6 rst_n $end
   $var wire  8 8 t [7:0] $end
   $var wire  1 7 valid_w $end
   $var wire 32 I w [31:0] $end
   $var wire 32 4 w_gen [31:0] $end
   $var wire 32 3 w_gen_temp [31:0] $end
  $upscope $end
 $upscope $end
$enddefinitions $end


#0
b00000000000000000000000000000000000000000000000000000000000000000000000000000000000000000000000000000000000000000000000000000000000000000000000000000000000000000000000000000000000000000000000000000000000000000000000000000000000000000000000000000000000000000000000000000000000000000000000000000000000000000000000000000000000000000000000000000000000000000000000000000000000000000000000000000000000000000000000000000000000000000000000000000000000000000000000000000000000000000000000000000000000000000000000000000000 #
b00000000000000000000000000000000 3
b00000000000000000000000000000000 4
15
06
07
b00000000 8
b00000000000000000000000000000000000000000000000000000000000000000000000000000000000000000000000000000000000000000000000000000000000000000000000000000000000000000000000000000000000000000000000000000000000000000000000000000000000000000000000000000000000000000000000000000000000000000000000000000000000000000000000000000000000000000000000000000000000000000000000000000000000000000000000000000000000000000000000000000000000000000000000000000000000000000000000000000000000000000000000000000000000000000000000000000001 9
b00000000000000000000000000000000 I
0J
b00000000000000000000000000000000000000000000000000000000000000000000000000000000000000000000000000000000000000000000000000000000000000000000000000000000000000000000000000000000000000000000000000000000000000000000000000000000000000000000000000000000000000000000000000000000000000000000000000000000000000000000000000000000000000000000000000000000000000000000000000000000000000000000000000000000000000000000000000000000000000000000000000000000000000000000000000000000000000000000000000000000000000000000000000000000 K
b00000000000000000000000000100000 [
#1
#2
#3
#4
#5
#6
#7
#8
#9
#10
05
#11
#12
#13
#14
#15
#16
#17
#18
#19
#20
15
#21
16
#22
#23
#24
#25
#26
#27
#28
#29
#30
05
#31
#32
#33
#34
#35
#36
#37
#38
#39
#40
15
#41
#42
#43
#44
#45
#46
#47
#48
#49
#50
05
#51
#52
#53
#54
#55
#56
#57
#58
#59
#60
b00000000000000000000000000000000000000000000000000000000000000000000000000000000000000000000000000000000000000000000000000000000000000000000000000000000000000000000000000000000000000000000000000000000000000000000000000000000000000000000000000000000000000000000000000000000000000000000000000000000000000000000000000000000000000000000000000000000000000000000000000000000000000000000000000000000000000000000000000000000000000000000000000000000000000000000000000000000000000000000000000000000000000000000000000000001 #
15
17
b00000000000000000000000000000000000000000000000000000000000000000000000000000000000000000000000000000000000000000000000000000000000000000000000000000000000000000000000000000000000000000000000000000000000000000000000000000000000000000000000000000000000000000000000000000000000000000000000000000000000000000000000000000000000000000000000000000000000000000000000000000000000000000000000000000000000000000000000000000000000000000000000000000000000000000000000000000000000000000000000100000000000000000000000000000000 K
#61
#62
#63
#64
#65
#66
#67
#68
#69
#70
05
#71
#72
#73
#74
#75
#76
#77
#78
#79
#80
b00000000000000000000000000000000000000000000000000000000000000000000000000000000000000000000000000000000000000000000000000000000000000000000000000000000000000000000000000000000000000000000000000000000000000000000000000000000000000000000000000000000000000000000000000000000000000000000000000000000000000000000000000000000000000000000000000000000000000000000000000000000000000000000000000000000000000000000000000000000000000000000000000000000000000000000000000000000000000000000000100000000000000000000000000000000 #
15
b00000001 8
b00000000000000000000000000000000000000000000000000000000000000000000000000000000000000000000000000000000000000000000000000000000000000000000000000000000000000000000000000000000000000000000000000000000000000000000000000000000000000000000000000000000000000000000000000000000000000000000000000000000000000000000000000000000000000000000000000000000000000000000000000000000000000000000000000000000000000000000000000000000000000000000000000000000000000010000000000000000000000000000000000000000000000000000000000000000 K
#81
#82
#83
#84
#85
#86
#87
#88
#89
#90
05
#91
#92
#93
#94
#95
#96
#97
#98
#99
#100
b00000000000000000000000000000000000000000000000000000000000000000000000000000000000000000000000000000000000000000000000000000000000000000000000000000000000000000000000000000000000000000000000000000000000000000000000000000000000000000000000000000000000000000000000000000000000000000000000000000000000000000000000000000000000000000000000000000000000000000000000000000000000000000000000000000000000000000000000000000000000000000000000000000000000000010000000000000000000000000000000000000000000000000000000000000000 #
b00000000000000000000000000000001 3
b00000000000000000000000000000010 4
15
b00000010 8
b00000000000000000000000000000000000000000000000000000000000000000000000000000000000000000000000000000000000000000000000000000000000000000000000000000000000000000000000000000000000000000000000000000000000000000000000000000000000000000000000000000000000000000000000000000000000000000000000000000000000000000000000000000000000000000000000000000000000000000000000000000000000000000000000000000000000000000000000000000001000000000000000000000000000000000000000000000000000000000000000000000000000000000000000000000000 K
#101
#102
#103
#104
#105
#106
#107
#108
#109
#110
05
#111
#112
#113
#114
#115
#116
#117
#118
#119
#120
b00000000000000000000000000000000000000000000000000000000000000000000000000000000000000000000000000000000000000000000000000000000000000000000000000000000000000000000000000000000000000000000000000000000000000000000000000000000000000000000000000000000000000000000000000000000000000000000000000000000000000000000000000000000000000000000000000000000000000000000000000000000000000000000000000000000000000000000000000000001000000000000000000000000000000000000000000000000000000000000000000000000000000000000000000000000 #
b00000000000000000000000000000000 3
b00000000000000000000000000000000 4
15
b00000011 8
b00000000000000000000000000000000000000000000000000000000000000000000000000000000000000000000000000000000000000000000000000000000000000000000000000000000000000000000000000000000000000000000000000000000000000000000000000000000000000000000000000000000000000000000000000000000000000000000000000000000000000000000000000000000000000000000000000000000000000000000000000000000000000000000000100000000000000000000000000000000000000000000000000000000000000000000000000000000000000000000000000000000000000000000000000000000 K
#121
#122
#123
#124
#125
#126
#127
#128
#129
#130
05
#131
#132
#133
#134
#135
#136
#137
#138
#139
#140
b00000000000000000000000000000000000000000000000000000000000000000000000000000000000000000000000000000000000000000000000000000000000000000000000000000000000000000000000000000000000000000000000000000000000000000000000000000000000000000000000000000000000000000000000000000000000000000000000000000000000000000000000000000000000000000000000000000000000000000000000000000000000000000000000100000000000000000000000000000000000000000000000000000000000000000000000000000000000000000000000000000000000000000000000000000000 #
15
b00000100 8
b00000000000000000000000000000000000000000000000000000000000000000000000000000000000000000000000000000000000000000000000000000000000000000000000000000000000000000000000000000000000000000000000000000000000000000000000000000000000000000000000000000000000000000000000000000000000000000000000000000000000000000000000000000000000000000000000000000000000000010000000000000000000000000000000000000000000000000000000000000000000000000000000000000000000000000000000000000000000000000000000000000000000000000000000000000000 K
#141
#142
#143
#144
#145
#146
#147
#148
#149
#150
05
#151
#152
#153
#154
#155
#156
#157
#158
#159
#160
b00000000000000000000000000000000000000000000000000000000000000000000000000000000000000000000000000000000000000000000000000000000000000000000000000000000000000000000000000000000000000000000000000000000000000000000000000000000000000000000000000000000000000000000000000000000000000000000000000000000000000000000000000000000000000000000000000000000000000010000000000000000000000000000000000000000000000000000000000000000000000000000000000000000000000000000000000000000000000000000000000000000000000000000000000000000 #
15
b00000101 8
b00000000000000000000000000000000000000000000000000000000000000000000000000000000000000000000000000000000000000000000000000000000000000000000000000000000000000000000000000000000000000000000000000000000000000000000000000000000000000000000000000000000000000000000000000000000000000000000000000000000000000000000000000000001000000000000000000000000000000000000000000000000000000000000000000000000000000000000000000000000000000000000000000000000000000000000000000000000000000000000000000000000000000000000000000000000 K
#161
#162
#163
#164
#165
#166
#167
#168
#169
#170
05
#171
#172
#173
#174
#175
#176
#177
#178
#179
#180
b00000000000000000000000000000000000000000000000000000000000000000000000000000000000000000000000000000000000000000000000000000000000000000000000000000000000000000000000000000000000000000000000000000000000000000000000000000000000000000000000000000000000000000000000000000000000000000000000000000000000000000000000000000001000000000000000000000000000000000000000000000000000000000000000000000000000000000000000000000000000000000000000000000000000000000000000000000000000000000000000000000000000000000000000000000000 #
15
b00000110 8
b00000000000000000000000000000000000000000000000000000000000000000000000000000000000000000000000000000000000000000000000000000000000000000000000000000000000000000000000000000000000000000000000000000000000000000000000000000000000000000000000000000000000000000000000000000000000000000000000100000000000000000000000000000000000000000000000000000000000000000000000000000000000000000000000000000000000000000000000000000000000000000000000000000000000000000000000000000000000000000000000000000000000000000000000000000000 K
#181
#182
#183
#184
#185
#186
#187
#188
#189
#190
05
#191
#192
#193
#194
#195
#196
#197
#198
#199
#200
b00000000000000000000000000000000000000000000000000000000000000000000000000000000000000000000000000000000000000000000000000000000000000000000000000000000000000000000000000000000000000000000000000000000000000000000000000000000000000000000000000000000000000000000000000000000000000000000000100000000000000000000000000000000000000000000000000000000000000000000000000000000000000000000000000000000000000000000000000000000000000000000000000000000000000000000000000000000000000000000000000000000000000000000000000000000 #
b00000000000000000000000000000001 3
b00000000000000000000000000000010 4
15
b00000111 8
b00000000000000000000000000000000000000000000000000000000000000000000000000000000000000000000000000000000000000000000000000000000000000000000000000000000000000000000000000000000000000000000000000000000000000000000000000000000000000000000000000000000000000010000000000000000000000000000000000000000000000000000000000000000000000000000000000000000000000000000000000000000000000000000000000000000000000000000000000000000000000000000000000000000000000000000000000000000000000000000000000000000000000000000000000000000 K
#201
#202
#203
#204
#205
#206
#207
#208
#209
#210
05
#211
#212
#213
#214
#215
#216
#217
#218
#219
#220
b00000000000000000000000000000000000000000000000000000000000000000000000000000000000000000000000000000000000000000000000000000000000000000000000000000000000000000000000000000000000000000000000000000000000000000000000000000000000000000000000000000000000000010000000000000000000000000000000000000000000000000000000000000000000000000000000000000000000000000000000000000000000000000000000000000000000000000000000000000000000000000000000000000000000000000000000000000000000000000000000000000000000000000000000000000000 #
b00000000000000000000000000000000 3
b00000000000000000000000000000000 4
15
b00001000 8
b00000000000000000000000000000000000000000000000000000000000000000000000000000000000000000000000000000000000000000000000000000000000000000000000000000000000000000000000000000000000000000000000000000000000000000000000000000001000000000000000000000000000000000000000000000000000000000000000000000000000000000000000000000000000000000000000000000000000000000000000000000000000000000000000000000000000000000000000000000000000000000000000000000000000000000000000000000000000000000000000000000000000000000000000000000000 K
#221
#222
#223
#224
#225
#226
#227
#228
#229
#230
05
#231
#232
#233
#234
#235
#236
#237
#238
#239
#240
b00000000000000000000000000000000000000000000000000000000000000000000000000000000000000000000000000000000000000000000000000000000000000000000000000000000000000000000000000000000000000000000000000000000000000000000000000000001000000000000000000000000000000000000000000000000000000000000000000000000000000000000000000000000000000000000000000000000000000000000000000000000000000000000000000000000000000000000000000000000000000000000000000000000000000000000000000000000000000000000000000000000000000000000000000000000 #
15
b00001001 8
b00000000000000000000000000000000000000000000000000000000000000000000000000000000000000000000000000000000000000000000000000000000000000000000000000000000000000000000000000000000000000000000000100000000000000000000000000000000000000000000000000000000000000000000000000000000000000000000000000000000000000000000000000000000000000000000000000000000000000000000000000000000000000000000000000000000000000000000000000000000000000000000000000000000000000000000000000000000000000000000000000000000000000000000000000000000 K
#241
#242
#243
#244
#245
#246
#247
#248
#249
#250
05
#251
#252
#253
#254
#255
#256
#257
#258
#259
#260
b00000000000000000000000000000000000000000000000000000000000000000000000000000000000000000000000000000000000000000000000000000000000000000000000000000000000000000000000000000000000000000000000100000000000000000000000000000000000000000000000000000000000000000000000000000000000000000000000000000000000000000000000000000000000000000000000000000000000000000000000000000000000000000000000000000000000000000000000000000000000000000000000000000000000000000000000000000000000000000000000000000000000000000000000000000000 #
15
b00001010 8
b00000000000000000000000000000000000000000000000000000000000000000000000000000000000000000000000000000000000000000000000000000000000000000000000000000000000000010000000000000000000000000000000000000000000000000000000000000000000000000000000000000000000000000000000000000000000000000000000000000000000000000000000000000000000000000000000000000000000000000000000000000000000000000000000000000000000000000000000000000000000000000000000000000000000000000000000000000000000000000000000000000000000000000000000000000000 K
#261
#262
#263
#264
#265
#266
#267
#268
#269
#270
05
#271
#272
#273
#274
#275
#276
#277
#278
#279
#280
b00000000000000000000000000000000000000000000000000000000000000000000000000000000000000000000000000000000000000000000000000000000000000000000000000000000000000010000000000000000000000000000000000000000000000000000000000000000000000000000000000000000000000000000000000000000000000000000000000000000000000000000000000000000000000000000000000000000000000000000000000000000000000000000000000000000000000000000000000000000000000000000000000000000000000000000000000000000000000000000000000000000000000000000000000000000 #
15
b00001011 8
b00000000000000000000000000000000000000000000000000000000000000000000000000000000000000000000000000000000000000000000000000000001000000000000000000000000000000000000000000000000000000000000000000000000000000000000000000000000000000000000000000000000000000000000000000000000000000000000000000000000000000000000000000000000000000000000000000000000000000000000000000000000000000000000000000000000000000000000000000000000000000000000000000000000000000000000000000000000000000000000000000000000000000000000000000000000 K
#281
#282
#283
#284
#285
#286
#287
#288
#289
#290
05
#291
#292
#293
#294
#295
#296
#297
#298
#299
#300
b00000000000000000000000000000000000000000000000000000000000000000000000000000000000000000000000000000000000000000000000000000001000000000000000000000000000000000000000000000000000000000000000000000000000000000000000000000000000000000000000000000000000000000000000000000000000000000000000000000000000000000000000000000000000000000000000000000000000000000000000000000000000000000000000000000000000000000000000000000000000000000000000000000000000000000000000000000000000000000000000000000000000000000000000000000000 #
15
b00001100 8
b00000000000000000000000000000000000000000000000000000000000000000000000000000000000000000000000100000000000000000000000000000000000000000000000000000000000000000000000000000000000000000000000000000000000000000000000000000000000000000000000000000000000000000000000000000000000000000000000000000000000000000000000000000000000000000000000000000000000000000000000000000000000000000000000000000000000000000000000000000000000000000000000000000000000000000000000000000000000000000000000000000000000000000000000000000000 K
#301
#302
#303
#304
#305
#306
#307
#308
#309
#310
05
#311
#312
#313
#314
#315
#316
#317
#318
#319
#320
b00000000000000000000000000000000000000000000000000000000000000000000000000000000000000000000000100000000000000000000000000000000000000000000000000000000000000000000000000000000000000000000000000000000000000000000000000000000000000000000000000000000000000000000000000000000000000000000000000000000000000000000000000000000000000000000000000000000000000000000000000000000000000000000000000000000000000000000000000000000000000000000000000000000000000000000000000000000000000000000000000000000000000000000000000000000 #
b00000000000000000000000000000001 3
b00000000000000000000000000000010 4
15
b00001101 8
b00000000000000000000000000000000000000000000000000000000000000010000000000000000000000000000000000000000000000000000000000000000000000000000000000000000000000000000000000000000000000000000000000000000000000000000000000000000000000000000000000000000000000000000000000000000000000000000000000000000000000000000000000000000000000000000000000000000000000000000000000000000000000000000000000000000000000000000000000000000000000000000000000000000000000000000000000000000000000000000000000000000000000000000000000000000 K
#321
#322
#323
#324
#325
#326
#327
#328
#329
#330
05
#331
#332
#333
#334
#335
#336
#337
#338
#339
#340
b00000000000000000000000000000000000000000000000000000000000000010000000000000000000000000000000000000000000000000000000000000000000000000000000000000000000000000000000000000000000000000000000000000000000000000000000000000000000000000000000000000000000000000000000000000000000000000000000000000000000000000000000000000000000000000000000000000000000000000000000000000000000000000000000000000000000000000000000000000000000000000000000000000000000000000000000000000000000000000000000000000000000000000000000000000000 #
b00000000000000000000000000000000 3
b00000000000000000000000000000000 4
15
b00001110 8
b00000000000000000000000000000001000000000000000000000000000000000000000000000000000000000000000000000000000000000000000000000000000000000000000000000000000000000000000000000000000000000000000000000000000000000000000000000000000000000000000000000000000000000000000000000000000000000000000000000000000000000000000000000000000000000000000000000000000000000000000000000000000000000000000000000000000000000000000000000000000000000000000000000000000000000000000000000000000000000000000000000000000000000000000000000000 K
#341
#342
#343
#344
#345
#346
#347
#348
#349
#350
05
#351
#352
#353
#354
#355
#356
#357
#358
#359
#360
b00000000000000000000000000000001000000000000000000000000000000000000000000000000000000000000000000000000000000000000000000000000000000000000000000000000000000000000000000000000000000000000000000000000000000000000000000000000000000000000000000000000000000000000000000000000000000000000000000000000000000000000000000000000000000000000000000000000000000000000000000000000000000000000000000000000000000000000000000000000000000000000000000000000000000000000000000000000000000000000000000000000000000000000000000000000 #
b00000000000000000000000000000001 3
b00000000000000000000000000000010 4
15
b00001111 8
b00000000000000000000000000000001 I
b00000000000000000000000000000000000000000000000000000000000000000000000000000000000000000000000000000000000000000000000000000000000000000000000000000000000000000000000000000000000000000000000000000000000000000000000000000000000000000000000000000000000000000000000000000000000000000000000000000000000000000000000000000000000000000000000000000000000000000000000000000000000000000000000000000000000000000000000000000000000000000000000000000000000000000000000000000000000000000000000000000000000000000000000000000001 K
#361
#362
#363
#364
#365
#366
#367
#368
#369
#370
05
#371
#372
#373
#374
#375
#376
#377
#378
#379
#380
b00000000000000000000000000000000000000000000000000000000000000000000000000000000000000000000000000000000000000000000000000000000000000000000000000000000000000000000000000000000000000000000000000000000000000000000000000000000000000000000000000000000000000000000000000000000000000000000000000000000000000000000000000000000000000000000000000000000000000000000000000000000000000000000000000000000000000000000000000000000000000000000000000000000000000000000000000000000000000000000000000000000000000000000000000000001 #
b00000000000000000000000000000000 3
b00000000000000000000000000000000 4
15
b00010000 8
b00000000000000000000000000000000 I
b00000000000000000000000000000000000000000000000000000000000000000000000000000000000000000000000000000000000000000000000000000000000000000000000000000000000000000000000000000000000000000000000000000000000000000000000000000000000000000000000000000000000000000000000000000000000000000000000000000000000000000000000000000000000000000000000000000000000000000000000000000000000000000000000000000000000000000000000000000000000000000000000000000000000000000000000000000000000000000000000100000000000000000000000000000000 K
#381
#382
#383
#384
#385
#386
#387
#388
#389
#390
05
#391
#392
#393
#394
#395
#396
#397
#398
#399
#400
b00000000000000000000000000000000000000000000000000000000000000000000000000000000000000000000000000000000000000000000000000000000000000000000000000000000000000000000000000000000000000000000000000000000000000000000000000000000000000000000000000000000000000000000000000000000000000000000000000000000000000000000000000000000000000000000000000000000000000000000000000000000000000000000000000000000000000000000000000000000000000000000000000000000000000000000000000000000000000000000000100000000000000000000000000000000 #
15
b00010001 8
b00000000000000000000000000000000000000000000000000000000000000000000000000000000000000000000000000000000000000000000000000000000000000000000000000000000000000000000000000000000000000000000000000000000000000000000000000000000000000000000000000000000000000000000000000000000000000000000000000000000000000000000000000000000000000000000000000000000000000000000000000000000000000000000000000000000000000000000000000000000000000000000000000000000000000010000000000000000000000000000000000000000000000000000000000000000 K
#401
#402
#403
#404
#405
#406
#407
#408
#409
#410
05
#411
#412
#413
#414
#415
#416
#417
#418
#419
#420
b00000000000000000000000000000000000000000000000000000000000000000000000000000000000000000000000000000000000000000000000000000000000000000000000000000000000000000000000000000000000000000000000000000000000000000000000000000000000000000000000000000000000000000000000000000000000000000000000000000000000000000000000000000000000000000000000000000000000000000000000000000000000000000000000000000000000000000000000000000000000000000000000000000000000000010000000000000000000000000000000000000000000000000000000000000000 #
b00000000000000000000000000000001 3
b00000000000000000000000000000010 4
15
b00010010 8
b00000000000000000000000000000010 I
b00000000000000000000000000000000000000000000000000000000000000000000000000000000000000000000000000000000000000000000000000000000000000000000000000000000000000000000000000000000000000000000000000000000000000000000000000000000000000000000000000000000000000000000000000000000000000000000000000000000000000000000000000000000000000000000000000000000000000000000000000000000000000000000000000000000000000000000000000000001000000000000000000000000000000000000000000000000000000000000000000000000000000000000000000000010 K
#421
#422
#423
#424
#425
#426
#427
#428
#429
#430
05
#431
#432
#433
#434
#435
#436
#437
#438
#439
#440
b00000000000000000000000000000000000000000000000000000000000000000000000000000000000000000000000000000000000000000000000000000000000000000000000000000000000000000000000000000000000000000000000000000000000000000000000000000000000000000000000000000000000000000000000000000000000000000000000000000000000000000000000000000000000000000000000000000000000000000000000000000000000000000000000000000000000000000000000000000001000000000000000000000000000000000000000000000000000000000000000000000000000000000000000000000010 #
b00000000000000000000000000000000 3
b00000000000000000000000000000000 4
15
b00010011 8
b00000000000000000000000000000000 I
b00000000000000000000000000000000000000000000000000000000000000000000000000000000000000000000000000000000000000000000000000000000000000000000000000000000000000000000000000000000000000000000000000000000000000000000000000000000000000000000000000000000000000000000000000000000000000000000000000000000000000000000000000000000000000000000000000000000000000000000000000000000000000000000000100000000000000000000000000000000000000000000000000000000000000000000000000000000000000000000001000000000000000000000000000000000 K
#441
#442
#443
#444
#445
#446
#447
#448
#449
#450
05
#451
#452
#453
#454
#455
#456
#457
#458
#459
#460
b00000000000000000000000000000000000000000000000000000000000000000000000000000000000000000000000000000000000000000000000000000000000000000000000000000000000000000000000000000000000000000000000000000000000000000000000000000000000000000000000000000000000000000000000000000000000000000000000000000000000000000000000000000000000000000000000000000000000000000000000000000000000000000000000100000000000000000000000000000000000000000000000000000000000000000000000000000000000000000000001000000000000000000000000000000000 #
15
b00010100 8
b00000000000000000000000000000000000000000000000000000000000000000000000000000000000000000000000000000000000000000000000000000000000000000000000000000000000000000000000000000000000000000000000000000000000000000000000000000000000000000000000000000000000000000000000000000000000000000000000000000000000000000000000000000000000000000000000000000000000000010000000000000000000000000000000000000000000000000000000000000000000000000000000000000000000000100000000000000000000000000000000000000000000000000000000000000000 K
#461
#462
#463
#464
#465
#466
#467
#468
#469
#470
05
#471
#472
#473
#474
#475
#476
#477
#478
#479
#480
b00000000000000000000000000000000000000000000000000000000000000000000000000000000000000000000000000000000000000000000000000000000000000000000000000000000000000000000000000000000000000000000000000000000000000000000000000000000000000000000000000000000000000000000000000000000000000000000000000000000000000000000000000000000000000000000000000000000000000010000000000000000000000000000000000000000000000000000000000000000000000000000000000000000000000100000000000000000000000000000000000000000000000000000000000000000 #
b00000000000000000000000000000010 3
b00000000000000000000000000000100 4
15
b00010101 8
b00000000000000000000000000000100 I
b00000000000000000000000000000000000000000000000000000000000000000000000000000000000000000000000000000000000000000000000000000000000000000000000000000000000000000000000000000000000000000000000000000000000000000000000000000000000000000000000000000000000000000000000000000000000000000000000000000000000000000000000000000001000000000000000000000000000000000000000000000000000000000000000000000000000000000000000000000010000000000000000000000000000000000000000000000000000000000000000000000000000000000000000000000100 K
#481
#482
#483
#484
#485
#486
#487
#488
#489
#490
05
#491
#492
#493
#494
#495
#496
#497
#498
#499
#500
b00000000000000000000000000000000000000000000000000000000000000000000000000000000000000000000000000000000000000000000000000000000000000000000000000000000000000000000000000000000000000000000000000000000000000000000000000000000000000000000000000000000000000000000000000000000000000000000000000000000000000000000000000000001000000000000000000000000000000000000000000000000000000000000000000000000000000000000000000000010000000000000000000000000000000000000000000000000000000000000000000000000000000000000000000000100 #
b00000000000000000000000000000000 3
b00000000000000000000000000000000 4
15
b00010110 8
b00000000000000000000000000000000 I
b00000000000000000000000000000000000000000000000000000000000000000000000000000000000000000000000000000000000000000000000000000000000000000000000000000000000000000000000000000000000000000000000000000000000000000000000000000000000000000000000000000000000000000000000000000000000000000000000100000000000000000000000000000000000000000000000000000000000000000000000000000000000000000000001000000000000000000000000000000000000000000000000000000000000000000000000000000000000000000000010000000000000000000000000000000000 K
#501
#502
#503
#504
#505
#506
#507
#508
#509
#510
05
#511
#512
#513
#514
#515
#516
#517
#518
#519
#520
b00000000000000000000000000000000000000000000000000000000000000000000000000000000000000000000000000000000000000000000000000000000000000000000000000000000000000000000000000000000000000000000000000000000000000000000000000000000000000000000000000000000000000000000000000000000000000000000000100000000000000000000000000000000000000000000000000000000000000000000000000000000000000000000001000000000000000000000000000000000000000000000000000000000000000000000000000000000000000000000010000000000000000000000000000000000 #
b00000000000000000000000000000001 3
b00000000000000000000000000000010 4
15
b00010111 8
b00000000000000000000000000000010 I
b00000000000000000000000000000000000000000000000000000000000000000000000000000000000000000000000000000000000000000000000000000000000000000000000000000000000000000000000000000000000000000000000000000000000000000000000000000000000000000000000000000000000000010000000000000000000000000000000000000000000000000000000000000000000000000000000000000000000000100000000000000000000000000000000000000000000000000000000000000000000000000000000000000000000001000000000000000000000000000000000000000000000000000000000000000010 K
#521
#522
#523
#524
#525
#526
#527
#528
#529
#530
05
#531
#532
#533
#534
#535
#536
#537
#538
#539
#540
b00000000000000000000000000000000000000000000000000000000000000000000000000000000000000000000000000000000000000000000000000000000000000000000000000000000000000000000000000000000000000000000000000000000000000000000000000000000000000000000000000000000000000010000000000000000000000000000000000000000000000000000000000000000000000000000000000000000000000100000000000000000000000000000000000000000000000000000000000000000000000000000000000000000000001000000000000000000000000000000000000000000000000000000000000000010 #
b00000000000000000000000000000100 3
b00000000000000000000000000001000 4
15
b00011000 8
b00000000000000000000000000001000 I
b00000000000000000000000000000000000000000000000000000000000000000000000000000000000000000000000000000000000000000000000000000000000000000000000000000000000000000000000000000000000000000000000000000000000000000000000000000001000000000000000000000000000000000000000000000000000000000000000000000000000000000000000000000010000000000000000000000000000000000000000000000000000000000000000000000000000000000000000000000100000000000000000000000000000000000000000000000000000000000000001000000000000000000000000000001000 K
#541
#542
#543
#544
#545
#546
#547
#548
#549
#550
05
#551
#552
#553
#554
#555
#556
#557
#558
#559
#560
b00000000000000000000000000000000000000000000000000000000000000000000000000000000000000000000000000000000000000000000000000000000000000000000000000000000000000000000000000000000000000000000000000000000000000000000000000000001000000000000000000000000000000000000000000000000000000000000000000000000000000000000000000000010000000000000000000000000000000000000000000000000000000000000000000000000000000000000000000000100000000000000000000000000000000000000000000000000000000000000001000000000000000000000000000001000 #
b00000000000000000000000000000000 3
b00000000000000000000000000000000 4
15
b00011001 8
b00000000000000000000000000000000 I
b00000000000000000000000000000000000000000000000000000000000000000000000000000000000000000000000000000000000000000000000000000000000000000000000000000000000000000000000000000000000000000000000100000000000000000000000000000000000000000000000000000000000000000000000000000000000000000000001000000000000000000000000000000000000000000000000000000000000000000000000000000000000000000000010000000000000000000000000000000000000000000000000000000000000000100000000000000000000000000000100000000000000000000000000000000000 K
#561
#562
#563
#564
#565
#566
#567
#568
#569
#570
05
#571
#572
#573
#574
#575
#576
#577
#578
#579
#580
b00000000000000000000000000000000000000000000000000000000000000000000000000000000000000000000000000000000000000000000000000000000000000000000000000000000000000000000000000000000000000000000000100000000000000000000000000000000000000000000000000000000000000000000000000000000000000000000001000000000000000000000000000000000000000000000000000000000000000000000000000000000000000000000010000000000000000000000000000000000000000000000000000000000000000100000000000000000000000000000100000000000000000000000000000000000 #
15
b00011010 8
b00000000000000000000000000000000000000000000000000000000000000000000000000000000000000000000000000000000000000000000000000000000000000000000000000000000000000010000000000000000000000000000000000000000000000000000000000000000000000000000000000000000000000100000000000000000000000000000000000000000000000000000000000000000000000000000000000000000000001000000000000000000000000000000000000000000000000000000000000000010000000000000000000000000000010000000000000000000000000000000000000000000000000000000000000000000 K
#581
#582
#583
#584
#585
#586
#587
#588
#589
#590
05
#591
#592
#593
#594
#595
#596
#597
#598
#599
#600
b00000000000000000000000000000000000000000000000000000000000000000000000000000000000000000000000000000000000000000000000000000000000000000000000000000000000000010000000000000000000000000000000000000000000000000000000000000000000000000000000000000000000000100000000000000000000000000000000000000000000000000000000000000000000000000000000000000000000001000000000000000000000000000000000000000000000000000000000000000010000000000000000000000000000010000000000000000000000000000000000000000000000000000000000000000000 #
b00000000000000000000000000001000 3
b00000000000000000000000000010000 4
15
b00011011 8
b00000000000000000000000000010000 I
b00000000000000000000000000000000000000000000000000000000000000000000000000000000000000000000000000000000000000000000000000000001000000000000000000000000000000000000000000000000000000000000000000000000000000000000000000000010000000000000000000000000000000000000000000000000000000000000000000000000000000000000000000000100000000000000000000000000000000000000000000000000000000000000001000000000000000000000000000001000000000000000000000000000000000000000000000000000000000000000000000000000000000000000000000010000 K
#601
#602
#603
#604
#605
#606
#607
#608
#609
#610
05
#611
#612
#613
#614
#615
#616
#617
#618
#619
#620
b00000000000000000000000000000000000000000000000000000000000000000000000000000000000000000000000000000000000000000000000000000001000000000000000000000000000000000000000000000000000000000000000000000000000000000000000000000010000000000000000000000000000000000000000000000000000000000000000000000000000000000000000000000100000000000000000000000000000000000000000000000000000000000000001000000000000000000000000000001000000000000000000000000000000000000000000000000000000000000000000000000000000000000000000000010000 #
b00000000000000000000000000000000 3
b00000000000000000000000000000000 4
15
b00011100 8
b00000000000000000000000000000000 I
b00000000000000000000000000000000000000000000000000000000000000000000000000000000000000000000000100000000000000000000000000000000000000000000000000000000000000000000000000000000000000000000001000000000000000000000000000000000000000000000000000000000000000000000000000000000000000000000010000000000000000000000000000000000000000000000000000000000000000100000000000000000000000000000100000000000000000000000000000000000000000000000000000000000000000000000000000000000000000000001000000000000000000000000000000000000 K
#621
#622
#623
#624
#625
#626
#627
#628
#629
#630
05
#631
#632
#633
#634
#635
#636
#637
#638
#639
