v/src/sha1_round.v
/**********************************************************
// Copyright 1891.06.02-2017.07.14
// Contact with 1098011272@qq.com
================ SHA1_round.v ======================
>> Author       : ZPN
>> Date         : 2022.09.26
>> Description  : SHA1 round function
  1、输入160 bits {ABCDE}，可以得到当前round的temp；
  2、输出160 bits {ABCDE}，移位变换后输出
>> note         : (1)To 
>>              : (2)My
>> V180121      : World.
************************************************************/
/* verilator lint_off UNSIGNED */
module sha1_round
    #(parameter N = 32)(
        input [159 : 0]  r_din    ,
        input [31  : 0]  w        ,
        input [7   : 0]  round    ,
//        input            valid_r  ,                  // round 有效信号
    
        output [159 : 0] r_dout     
//        output           ready_r                    // 80 轮加密结束后拉高
);

    //循环所用函数
    reg [N-1: 0] f;
    reg [N-1: 0] k;
    wire [N-1: 0] a_shift, b_shift, add_result;
    wire [N-1: 0] a = r_din[159: 128];
    wire [N-1: 0] b = r_din[127: 96 ];
    wire [N-1: 0] c = r_din[95 : 64 ];
    wire [N-1: 0] d = r_din[63 : 32 ];
    wire [N-1: 0] e = r_din[31 : 0 ];

    always@ (*) begin
        k = 32'd0;
        if((round >= 8'd0 ) && (round <= 8'd19)) k = 32'h5A82_7999;
        if((round >= 8'd20) && (round <= 8'd39)) k = 32'h6ED9_EBA1;
        if((round >= 8'd40) && (round <= 8'd59)) k = 32'h8F1B_BCDC;
        if((round >= 8'd60) && (round <= 8'd79)) k = 32'hCA62_C1D6;
    end

    always@ (*) begin
        f = 32'h0;
        if((round >= 8'd0 ) && (round <= 8'd19)) f = ((b & c) | (~b & d));
        if((round >= 8'd20) && (round <= 8'd39)) f = (b ^ c ^ d);
        if((round >= 8'd40) && (round <= 8'd59)) f = ((b & c) | (b & d) | (c & d));
        if((round >= 8'd60) && (round <= 8'd79)) f = (b ^ c ^ d);
    end

    assign a_shift = {a[26: 0], a[31:27]};
    assign b_shift = {b[1 : 0], b[31: 2]};
    assign add_result = (a_shift + ((f + k) + (e + w)));
    assign r_dout = {add_result, a, b_shift, c, d};

endmodule

v/src/sha1_w.v
/**********************************************************
// Copyright open source
// Contact with 1098011272@qq.com
================ sha1.v ======================
>> Author       : ZPN
>> Date         : 2022.09.26
>> Description  : SHA1 module that generates w
************************************************************/
/* verilator lint_off UNSIGNED */

module sha1_w
  #(parameter N = 32)(
    input          clk   ,
    input          rst_n ,
    input          valid_w ,
    input [7   :0] t     ,
    input [511 :0] din   ,

    output [N-1 :0] w    
//    output          ready_w 
);
  reg [511: 0] din_temp;
  wire [511: 0] din_temp_shift ;
//----------------------------------------------------------------
// The din_temp is 16*32 bits in size and can computes the next w.
  always @(posedge clk or negedge rst_n ) begin
    if(!rst_n) begin
      din_temp <= 512'h0 ;
    end else if((t == 8'd0) && valid_w) begin
      din_temp <= din    ;
    end else if((t >= 8'd1) && (t <= 8'd79)) begin
      din_temp <= din_temp_shift ;
    end else 
      din_temp <= 512'h0;
  end

//---------------------------------------------------------------
  wire [N-1 :0] w_gen_temp = din_temp[511: 480] ^ din_temp[447: 416] ^ din_temp[255: 224] ^ din_temp[95: 64];
  wire [N-1 :0] w_gen = {w_gen_temp[30: 0], w_gen_temp[31]};      // generate new w

// the first fifteen is din ,and next is w_gen
  assign din_temp_shift = ((t >= 8'd0) && (t <= 8'd15)) ? {din_temp[479: 0], din_temp[511: 480]} :
                          (t >= 8'd16) && (t <= 8'd79)  ? {din_temp[479: 0], w_gen}              : 512'h0;

  assign w= ((t >= 8'd0) && (t <= 8'd15)) ? din_temp[511: 480] : w_gen;
//  assign ready_w = (t == 8'd79);

endmodule

v/src/sha1_con.v
module sha1_con(
  input         clk     ,
  input         rst_n   ,
  input         valid   ,

  output [7 :0] t       ,
  output        ready_t
);

  parameter IDLE  = 2'b00;
  parameter ROUND = 2'b01;
  parameter DONE  = 2'b10;

  reg [7 :0] t_tem;
  reg [1 :0] s_cur, s_next;

  //-------------------------- First state machine -------------------------------
  always @(posedge clk or negedge rst_n) begin
    if(!rst_n) begin
      s_cur <= IDLE;
    end
    else begin
      s_cur <= s_next;
    end
  end

//-------------------------- Second state machine -------------------------------
  always @(*) begin
    case (s_cur)
      IDLE:begin
        if(valid) begin
          s_next = ROUND;
        end
        else s_next = IDLE;
      end

      ROUND: begin
        if(t < 8'h4e) begin
          s_next = ROUND;
        end
        else if (t == 8'h4e) begin
          s_next = DONE;
        end
        else begin
          s_next = IDLE;
        end
      end

      DONE: begin
        s_next = IDLE;
      end
      default: s_next = IDLE;
    endcase
  end

//-------------------------- Third state machine -------------------------------
  always @(posedge clk or negedge rst_n) begin
    if(!rst_n)
      t_tem <= 8'b0;
    else if(s_cur == ROUND) begin
      t_tem <= t_tem + 1'b1;
    end
    else if(s_cur == DONE) begin
      t_tem <= t_tem;
    end
    else begin
      t_tem <= 8'b0;
    end
  end
  
//-------------------------------- Result --------------------------------------
  assign ready_t = ((s_cur == DONE) && (t == 8'h4f)) ;
  assign t = t_tem;

endmodule

v/src/sha1_top.v
/**********************************************************
// Copyright open source
// Contact with 1098011272@qq.com
================ sha1.v ======================
>> Author       : ZPN
>> Date         : 2022.09.29
>> Description  : SHA1 TOP module
************************************************************/

module sha1_top (
  input          clk   ,
  input          rst_n ,
  input          valid ,
  input [511: 0] din   ,

  output [159: 0] dout ,
  output          ready
);
  parameter H0 = 32'h6745_2301;
  parameter H1 = 32'hEFCD_AB89;
  parameter H2 = 32'h98BA_DCFE;
  parameter H3 = 32'h1032_5476;
  parameter H4 = 32'hC3D2_E1F0;

  wire [7 : 0] t;
  wire [31: 0] w_temp;
  wire [159 : 0] r_din_temp;
  reg  [159 : 0] r_din;

always @(posedge clk or negedge rst_n) begin
  if(!rst_n) begin
    r_din <= 0;
  end else if(t == 8'd0) begin
    r_din <= {H0, H1, H2, H3, H4};
  end else if(t > 8'd0 && t < 8'd80) begin
    r_din <= r_din_temp;
  end else begin
    r_din <= 0;
  end
end

  sha1_con u_con (
    .clk   (clk  ),
    .rst_n (rst_n),
    .valid (valid),

    .t       (t     ),
    .ready_t ( ready)
  );

  sha1_w u_w (
    .clk     (clk   ),
    .rst_n   (rst_n ),
    .valid_w (valid ),
    .t       (t     ),
    .din     (din   ),

    .w       (w_temp )
//    .ready_w (ready  )
  );

  sha1_round u_round (
    .r_din (r_din  ),
    .w     (w_temp ),
    .round (t      ),

    .r_dout (r_din_temp)
  );
  assign dout = (t == 8'd79) ? r_din_temp: 160'd0;
//  assign ready = (t == 8'd79);

endmodule

build/dump.vcd
$version Generated by VerilatedVcd $end
$date Thu Sep 29 10:56:48 2022 $end
$timescale 1ps $end

 $scope module TOP $end
  $var wire  1 \ clk $end
  $var wire 512 _ din [511:0] $end
  $var wire 160 o dout [159:0] $end
  $var wire  1 t ready $end
  $var wire  1 ] rst_n $end
  $var wire  1 ^ valid $end
  $scope module sha1_top $end
   $var wire 32 v H0 [31:0] $end
   $var wire 32 w H1 [31:0] $end
   $var wire 32 x H2 [31:0] $end
   $var wire 32 y H3 [31:0] $end
   $var wire 32 z H4 [31:0] $end
   $var wire  1 \ clk $end
   $var wire 512 _ din [511:0] $end
   $var wire 160 o dout [159:0] $end
   $var wire 160 * r_din [159:0] $end
   $var wire 160 % r_din_temp [159:0] $end
   $var wire  1 t ready $end
   $var wire  1 ] rst_n $end
   $var wire  8 # t [7:0] $end
   $var wire  1 ^ valid $end
   $var wire 32 $ w_temp [31:0] $end
   $scope module u_con $end
    $var wire  2 } DONE [1:0] $end
    $var wire  2 { IDLE [1:0] $end
    $var wire  2 | ROUND [1:0] $end
    $var wire  1 \ clk $end
    $var wire  1 t ready_t $end
    $var wire  1 ] rst_n $end
    $var wire  2 / s_cur [1:0] $end
    $var wire  2 u s_next [1:0] $end
    $var wire  8 # t [7:0] $end
    $var wire  8 # t_tem [7:0] $end
    $var wire  1 ^ valid $end
   $upscope $end
   $scope module u_round $end
    $var wire 32 ~ N [31:0] $end
    $var wire 32 W a [31:0] $end
    $var wire 32 T a_shift [31:0] $end
    $var wire 32 V add_result [31:0] $end
    $var wire 32 X b [31:0] $end
    $var wire 32 U b_shift [31:0] $end
    $var wire 32 Y c [31:0] $end
    $var wire 32 Z d [31:0] $end
    $var wire 32 [ e [31:0] $end
    $var wire 32 R f [31:0] $end
    $var wire 32 S k [31:0] $end
    $var wire 160 * r_din [159:0] $end
    $var wire 160 % r_dout [159:0] $end
    $var wire  8 # round [7:0] $end
    $var wire 32 $ w [31:0] $end
   $upscope $end
   $scope module u_w $end
    $var wire 32 ~ N [31:0] $end
    $var wire  1 \ clk $end
    $var wire 512 _ din [511:0] $end
    $var wire 512 0 din_temp [511:0] $end
    $var wire 512 @ din_temp_shift [511:0] $end
    $var wire  1 ] rst_n $end
    $var wire  8 # t [7:0] $end
    $var wire  1 ^ valid_w $end
    $var wire 32 $ w [31:0] $end
    $var wire 32 Q w_gen [31:0] $end
    $var wire 32 P w_gen_temp [31:0] $end
   $upscope $end
  $upscope $end
 $upscope $end
$enddefinitions $end


#0
b00000000 #
b00000000000000000000000000000000 $
b0101101010000010011110011001100100000000000000000000000000000000000000000000000000000000000000000000000000000000000000000000000000000000000000000000000000000000 %
b0000000000000000000000000000000000000000000000000000000000000000000000000000000000000000000000000000000000000000000000000000000000000000000000000000000000000000 *
b00 /
b00000000000000000000000000000000000000000000000000000000000000000000000000000000000000000000000000000000000000000000000000000000000000000000000000000000000000000000000000000000000000000000000000000000000000000000000000000000000000000000000000000000000000000000000000000000000000000000000000000000000000000000000000000000000000000000000000000000000000000000000000000000000000000000000000000000000000000000000000000000000000000000000000000000000000000000000000000000000000000000000000000000000000000000000000000000 0
b00000000000000000000000000000000000000000000000000000000000000000000000000000000000000000000000000000000000000000000000000000000000000000000000000000000000000000000000000000000000000000000000000000000000000000000000000000000000000000000000000000000000000000000000000000000000000000000000000000000000000000000000000000000000000000000000000000000000000000000000000000000000000000000000000000000000000000000000000000000000000000000000000000000000000000000000000000000000000000000000000000000000000000000000000000000 @
b00000000000000000000000000000000 P
b00000000000000000000000000000000 Q
b00000000000000000000000000000000 R
b01011010100000100111100110011001 S
b00000000000000000000000000000000 T
b00000000000000000000000000000000 U
b01011010100000100111100110011001 V
b00000000000000000000000000000000 W
b00000000000000000000000000000000 X
b00000000000000000000000000000000 Y
b00000000000000000000000000000000 Z
b00000000000000000000000000000000 [
1\
0]
0^
b00000000000000000000000000000000000000000000000000000000000000000000000000000000000000000000000000000000000000000000000000000000000000000000000000000000000000000000000000000000000000000000000000000000000000000000000000000000000000000000000000000000000000000000000000000000000000000000000000000000000000000000000000000000000000000000000000000000000000000000000000000000000000000000000000000000000000000000000000000000000000000000000000000000000000000000000000000000000000000000000000000000000000000000000000000000 _
b0000000000000000000000000000000000000000000000000000000000000000000000000000000000000000000000000000000000000000000000000000000000000000000000000000000000000000 o
0t
b00 u
b01100111010001010010001100000001 v
b11101111110011011010101110001001 w
b10011000101110101101110011111110 x
b00010000001100100101010001110110 y
b11000011110100101110000111110000 z
b00 {
b01 |
b10 }
b00000000000000000000000000100000 ~
#1
#2
#3
#4
#5
#6
#7
#8
#9
#10
0\
#11
#12
#13
#14
#15
#16
#17
#18
#19
#20
1\
#21
1]
#22
#23
#24
#25
#26
#27
#28
#29
#30
0\
#31
#32
#33
#34
#35
#36
#37
#38
#39
#40
b1001111110110100100110001011001101100111010001010010001100000001011110111111001101101010111000101001100010111010110111001111111000010000001100100101010001110110 %
b0110011101000101001000110000000111101111110011011010101110001001100110001011101011011100111111100001000000110010010101000111011011000011110100101110000111110000 *
b10011000101110101101110011111110 R
b11101000101001000110000000101100 T
b01111011111100110110101011100010 U
b10011111101101001001100010110011 V
b01100111010001010010001100000001 W
b11101111110011011010101110001001 X
b10011000101110101101110011111110 Y
b00010000001100100101010001110110 Z
b11000011110100101110000111110000 [
1\
#41
#42
#43
#44
#45
#46
#47
#48
#49
#50
0\
#51
#52
#53
#54
#55
#56
#57
#58
#59
#60
b00000000000000000000000000000001 $
b1001111110110100100110001011010001100111010001010010001100000001011110111111001101101010111000101001100010111010110111001111111000010000001100100101010001110110 %
b00000000000000000000000000000001000000000000000000000000000000000000000000000000000000000000000000000000000000000000000000000000000000000000000000000000000000000000000000000000000000000000000000000000000000000000000000000000000000000000000000000000000000000000000000000000000000000000000000000000000000000000000000000000000000000000000000000000000000000000000000000000000000000000000000000000000000000000000000000000000000000000000000000000000000000000000000000000000000000000000000000000000000000000000000000001 0
b00000000000000000000000000000000000000000000000000000000000000000000000000000000000000000000000000000000000000000000000000000000000000000000000000000000000000000000000000000000000000000000000000000000000000000000000000000000000000000000000000000000000000000000000000000000000000000000000000000000000000000000000000000000000000000000000000000000000000000000000000000000000000000000000000000000000000000000000000000000000000000000000000000000000000000000000000000000000000000000000100000000000000000000000000000001 @
b00000000000000000000000000000001 P
b00000000000000000000000000000010 Q
b10011111101101001001100010110100 V
1\
1^
b00000000000000000000000000000001000000000000000000000000000000000000000000000000000000000000000000000000000000000000000000000000000000000000000000000000000000000000000000000000000000000000000000000000000000000000000000000000000000000000000000000000000000000000000000000000000000000000000000000000000000000000000000000000000000000000000000000000000000000000000000000000000000000000000000000000000000000000000000000000000000000000000000000000000000000000000000000000000000000000000000000000000000000000000000000001 _
b01 u
#61
#62
#63
#64
#65
#66
#67
#68
#69
#70
0\
#71
#72
#73
#74
#75
#76
#77
#78
#79
#80
b01 /
1\
#81
#82
#83
#84
#85
#86
#87
#88
#89
#90
0\
#91
#92
#93
#94
#95
#96
#97
#98
#99
#100
b00000001 #
1\
#101
#102
#103
#104
#105
#106
#107
#108
#109
#110
0\
#111
#112
#113
#114
#115
#116
#117
#118
#119
#120
b00000010 #
b00000000000000000000000000000000 $
b0101110101000011111000111010000010011111101101001001100010110100010110011101000101001000110000000111101111110011011010101110001010011000101110101101110011111110 %
b1001111110110100100110001011010001100111010001010010001100000001011110111111001101101010111000101001100010111010110111001111111000010000001100100101010001110110 *
b00000000000000000000000000000000000000000000000000000000000000000000000000000000000000000000000000000000000000000000000000000000000000000000000000000000000000000000000000000000000000000000000000000000000000000000000000000000000000000000000000000000000000000000000000000000000000000000000000000000000000000000000000000000000000000000000000000000000000000000000000000000000000000000000000000000000000000000000000000000000000000000000000000000000000000000000000000000000000000000000100000000000000000000000000000001 0
b00000000000000000000000000000000000000000000000000000000000000000000000000000000000000000000000000000000000000000000000000000000000000000000000000000000000000000000000000000000000000000000000000000000000000000000000000000000000000000000000000000000000000000000000000000000000000000000000000000000000000000000000000000000000000000000000000000000000000000000000000000000000000000000000000000000000000000000000000000000000000000000000000000000000000010000000000000000000000000000000100000000000000000000000000000000 @
b00000000000000000000000000000000 P
b00000000000000000000000000000000 Q
b11111011111110111111111011111110 R
b11110110100100110001011010010011 T
b01011001110100010100100011000000 U
b01011101010000111110001110100000 V
b10011111101101001001100010110100 W
b01100111010001010010001100000001 X
b01111011111100110110101011100010 Y
b10011000101110101101110011111110 Z
b00010000001100100101010001110110 [
1\
#121
#122
#123
#124
#125
#126
#127
#128
#129
#130
0\
#131
#132
#133
#134
#135
#136
#137
#138
#139
#140
b00000011 #
b0001010110001101001101010110010001011101010000111110001110100000001001111110110100100110001011010101100111010001010010001100000001111011111100110110101011100010 %
b0101110101000011111000111010000010011111101101001001100010110100010110011101000101001000110000000111101111110011011010101110001010011000101110101101110011111110 *
b00000000000000000000000000000000000000000000000000000000000000000000000000000000000000000000000000000000000000000000000000000000000000000000000000000000000000000000000000000000000000000000000000000000000000000000000000000000000000000000000000000000000000000000000000000000000000000000000000000000000000000000000000000000000000000000000000000000000000000000000000000000000000000000000000000000000000000000000000000000000000000000000000000000000000010000000000000000000000000000000100000000000000000000000000000000 0
b00000000000000000000000000000000000000000000000000000000000000000000000000000000000000000000000000000000000000000000000000000000000000000000000000000000000000000000000000000000000000000000000000000000000000000000000000000000000000000000000000000000000000000000000000000000000000000000000000000000000000000000000000000000000000000000000000000000000000000000000000000000000000000000000000000000000000000000000000000001000000000000000000000000000000010000000000000000000000000000000000000000000000000000000000000000 @
b00000000000000000000000000000001 P
b00000000000000000000000000000010 Q
b01111001110100110110101011000010 R
b10101000011111000111010000001011 T
b00100111111011010010011000101101 U
b00010101100011010011010101100100 V
b01011101010000111110001110100000 W
b10011111101101001001100010110100 X
b01011001110100010100100011000000 Y
b01111011111100110110101011100010 Z
b10011000101110101101110011111110 [
1\
#141
#142
#143
#144
#145
#146
#147
#148
#149
#150
0\
#151
#152
#153
#154
#155
#156
#157
#158
#159
#160
b00000100 #
b1000110111101101101110110101110100010101100011010011010101100100000101110101000011111000111010000010011111101101001001100010110101011001110100010100100011000000 %
b0001010110001101001101010110010001011101010000111110001110100000001001111110110100100110001011010101100111010001010010001100000001111011111100110110101011100010 *
b00000000000000000000000000000000000000000000000000000000000000000000000000000000000000000000000000000000000000000000000000000000000000000000000000000000000000000000000000000000000000000000000000000000000000000000000000000000000000000000000000000000000000000000000000000000000000000000000000000000000000000000000000000000000000000000000000000000000000000000000000000000000000000000000000000000000000000000000000000001000000000000000000000000000000010000000000000000000000000000000000000000000000000000000000000000 0
b00000000000000000000000000000000000000000000000000000000000000000000000000000000000000000000000000000000000000000000000000000000000000000000000000000000000000000000000000000000000000000000000000000000000000000000000000000000000000000000000000000000000000000000000000000000000000000000000000000000000000000000000000000000000000000000000000000000000000000000000000000000000000000000000100000000000000000000000000000001000000000000000000000000000000000000000000000000000000000000000000000000000000000000000000000000 @
b00000101110100010010101001100000 R
b10110001101001101010110010000010 T
b00010111010100001111100011101000 U
b10001101111011011011101101011101 V
b00010101100011010011010101100100 W
b01011101010000111110001110100000 X
b00100111111011010010011000101101 Y
b01011001110100010100100011000000 Z
b01111011111100110110101011100010 [
1\
#161
#162
#163
#164
#165
#166
#167
#168
#169
#170
0\
#171
#172
#173
#174
#175
#176
#177
#178
#179
#180
b00000101 #
b1010100101101011011000000111001110001101111011011011101101011101000001010110001101001101010110010001011101010000111110001110100000100111111011010010011000101101 %
b1000110111101101101110110101110100010101100011010011010101100100000101110101000011111000111010000010011111101101001001100010110101011001110100010100100011000000 *
b00000000000000000000000000000000000000000000000000000000000000000000000000000000000000000000000000000000000000000000000000000000000000000000000000000000000000000000000000000000000000000000000000000000000000000000000000000000000000000000000000000000000000000000000000000000000000000000000000000000000000000000000000000000000000000000000000000000000000000000000000000000000000000000000100000000000000000000000000000001000000000000000000000000000000000000000000000000000000000000000000000000000000000000000000000000 0
b00000000000000000000000000000000000000000000000000000000000000000000000000000000000000000000000000000000000000000000000000000000000000000000000000000000000000000000000000000000000000000000000000000000000000000000000000000000000000000000000000000000000000000000000000000000000000000000000000000000000000000000000000000000000000000000000000000000000000010000000000000000000000000000000100000000000000000000000000000000000000000000000000000000000000000000000000000000000000000000000000000000000000000000000000000000 @
b00000000000000000000000000000000 P
b00000000000000000000000000000000 Q
b00110111011000000011001001101001 R
b10111101101101110110101110110001 T
b00000101011000110100110101011001 U
b10101001011010110110000001110011 V
b10001101111011011011101101011101 W
b00010101100011010011010101100100 X
b00010111010100001111100011101000 Y
b00100111111011010010011000101101 Z
b01011001110100010100100011000000 [
1\
#181
#182
#183
#184
#185
#186
#187
#188
#189
#190
0\
#191
#192
#193
#194
#195
#196
#197
#198
#199
#200
b00000110 #
b1100011101001100111110000011010010101001011010110110000001110011011000110111101101101110110101110000010101100011010011010101100100010111010100001111100011101000 %
b1010100101101011011000000111001110001101111011011011101101011101000001010110001101001101010110010001011101010000111110001110100000100111111011010010011000101101 *
b00000000000000000000000000000000000000000000000000000000000000000000000000000000000000000000000000000000000000000000000000000000000000000000000000000000000000000000000000000000000000000000000000000000000000000000000000000000000000000000000000000000000000000000000000000000000000000000000000000000000000000000000000000000000000000000000000000000000000010000000000000000000000000000000100000000000000000000000000000000000000000000000000000000000000000000000000000000000000000000000000000000000000000000000000000000 0
b00000000000000000000000000000000000000000000000000000000000000000000000000000000000000000000000000000000000000000000000000000000000000000000000000000000000000000000000000000000000000000000000000000000000000000000000000000000000000000000000000000000000000000000000000000000000000000000000000000000000000000000000000000001000000000000000000000000000000010000000000000000000000000000000000000000000000000000000000000000000000000000000000000000000000000000000000000000000000000000000000000000000000000000000000000000 @
b00010111011100010100100111111001 R
b00101101011011000000111001110101 T
b01100011011110110110111011010111 U
b11000111010011001111100000110100 V
b10101001011010110110000001110011 W
b10001101111011011011101101011101 X
b00000101011000110100110101011001 Y
b00010111010100001111100011101000 Z
b00100111111011010010011000101101 [
1\
#201
#202
#203
#204
#205
#206
#207
#208
#209
#210
0\
#211
#212
#213
#214
#215
#216
#217
#218
#219
#220
b00000111 #
b1000000011011101111001100111010011000111010011001111100000110100111010100101101011011000000111000110001101111011011011101101011100000101011000110100110101011001 %
b1100011101001100111110000011010010101001011010110110000001110011011000110111101101101110110101110000010101100011010011010101100100010111010100001111100011101000 *
b00000000000000000000000000000000000000000000000000000000000000000000000000000000000000000000000000000000000000000000000000000000000000000000000000000000000000000000000000000000000000000000000000000000000000000000000000000000000000000000000000000000000000000000000000000000000000000000000000000000000000000000000000000001000000000000000000000000000000010000000000000000000000000000000000000000000000000000000000000000000000000000000000000000000000000000000000000000000000000000000000000000000000000000000000000000 0
b00000000000000000000000000000000000000000000000000000000000000000000000000000000000000000000000000000000000000000000000000000000000000000000000000000000000000000000000000000000000000000000000000000000000000000000000000000000000000000000000000000000000000000000000000000000000000000000000100000000000000000000000000000001000000000000000000000000000000000000000000000000000000000000000000000000000000000000000000000000000000000000000000000000000000000000000000000000000000000000000000000000000000000000000000000000 @
b00100101011010110110110101011011 R
b11101001100111110000011010011000 T
b11101010010110101101100000011100 U
b10000000110111011110011001110100 V
b11000111010011001111100000110100 W
b10101001011010110110000001110011 X
b01100011011110110110111011010111 Y
b00000101011000110100110101011001 Z
b00010111010100001111100011101000 [
1\
#221
#222
#223
#224
#225
#226
#227
#228
#229
#230
0\
#231
#232
#233
#234
#235
#236
#237
#238
#239
#240
b00001000 #
b0101111000011110011101000101100110000000110111011110011001110100001100011101001100111110000011011110101001011010110110000001110001100011011110110110111011010111 %
b1000000011011101111001100111010011000111010011001111100000110100111010100101101011011000000111000110001101111011011011101101011100000101011000110100110101011001 *
b00000000000000000000000000000000000000000000000000000000000000000000000000000000000000000000000000000000000000000000000000000000000000000000000000000000000000000000000000000000000000000000000000000000000000000000000000000000000000000000000000000000000000000000000000000000000000000000000100000000000000000000000000000001000000000000000000000000000000000000000000000000000000000000000000000000000000000000000000000000000000000000000000000000000000000000000000000000000000000000000000000000000000000000000000000000 0
b00000000000000000000000000000000000000000000000000000000000000000000000000000000000000000000000000000000000000000000000000000000000000000000000000000000000000000000000000000000000000000000000000000000000000000000000000000000000000000000000000000000000000010000000000000000000000000000000100000000000000000000000000000000000000000000000000000000000000000000000000000000000000000000000000000000000000000000000000000000000000000000000000000000000000000000000000000000000000000000000000000000000000000000000000000000 @
b00000000000000000000000000000001 P
b00000000000000000000000000000010 Q
b11100010011110111101111011010111 R
b00011011101111001100111010010000 T
b00110001110100110011111000001101 U
b01011110000111100111010001011001 V
b10000000110111011110011001110100 W
b11000111010011001111100000110100 X
b11101010010110101101100000011100 Y
b01100011011110110110111011010111 Z
b00000101011000110100110101011001 [
1\
#241
#242
#243
#244
#245
#246
#247
#248
#249
#250
0\
#251
#252
#253
#254
#255
#256
#257
#258
#259
#260
b00001001 #
b1110110010011111101100011010011101011110000111100111010001011001001000000011011101111001100111010011000111010011001111100000110111101010010110101101100000011100 %
b0101111000011110011101000101100110000000110111011110011001110100001100011101001100111110000011011110101001011010110110000001110001100011011110110110111011010111 *
b00000000000000000000000000000000000000000000000000000000000000000000000000000000000000000000000000000000000000000000000000000000000000000000000000000000000000000000000000000000000000000000000000000000000000000000000000000000000000000000000000000000000000010000000000000000000000000000000100000000000000000000000000000000000000000000000000000000000000000000000000000000000000000000000000000000000000000000000000000000000000000000000000000000000000000000000000000000000000000000000000000000000000000000000000000000 0
b00000000000000000000000000000000000000000000000000000000000000000000000000000000000000000000000000000000000000000000000000000000000000000000000000000000000000000000000000000000000000000000000000000000000000000000000000000001000000000000000000000000000000010000000000000000000000000000000000000000000000000000000000000000000000000000000000000000000000000000000000000000000000000000000000000000000000000000000000000000000000000000000000000000000000000000000000000000000000000000000000000000000000000000000000000000 @
b01101010110100110011111000001100 R
b11000011110011101000101100101011 T
b00100000001101110111100110011101 U
b11101100100111111011000110100111 V
b01011110000111100111010001011001 W
b10000000110111011110011001110100 X
b00110001110100110011111000001101 Y
b11101010010110101101100000011100 Z
b01100011011110110110111011010111 [
1\
#261
#262
#263
#264
#265
#266
#267
#268
#269
#270
0\
#271
#272
#273
#274
#275
#276
#277
#278
#279
#280
b00001010 #
b1111101010101011000000001100111111101100100111111011000110100111010101111000011110011101000101100010000000110111011110011001110100110001110100110011111000001101 %
b1110110010011111101100011010011101011110000111100111010001011001001000000011011101111001100111010011000111010011001111100000110111101010010110101101100000011100 *
b00000000000000000000000000000000000000000000000000000000000000000000000000000000000000000000000000000000000000000000000000000000000000000000000000000000000000000000000000000000000000000000000000000000000000000000000000000001000000000000000000000000000000010000000000000000000000000000000000000000000000000000000000000000000000000000000000000000000000000000000000000000000000000000000000000000000000000000000000000000000000000000000000000000000000000000000000000000000000000000000000000000000000000000000000000000 0
b00000000000000000000000000000000000000000000000000000000000000000000000000000000000000000000000000000000000000000000000000000000000000000000000000000000000000000000000000000000000000000000000100000000000000000000000000000001000000000000000000000000000000000000000000000000000000000000000000000000000000000000000000000000000000000000000000000000000000000000000000000000000000000000000000000000000000000000000000000000000000000000000000000000000000000000000000000000000000000000000000000000000000000000000000000000 @
b00000000000000000000000000000000 P
b00000000000000000000000000000000 Q
b00100001110101110111101000011101 R
b10010011111101100011010011111101 T
b01010111100001111001110100010110 U
b11111010101010110000000011001111 V
b11101100100111111011000110100111 W
b01011110000111100111010001011001 X
b00100000001101110111100110011101 Y
b00110001110100110011111000001101 Z
b11101010010110101101100000011100 [
1\
#281
#282
#283
#284
#285
#286
#287
#288
#289
#290
0\
#291
#292
#293
#294
#295
#296
#297
#298
#299
#300
b00001011 #
b0010011001011101101010101100001111111010101010110000000011001111111110110010011111101100011010010101011110000111100111010001011000100000001101110111100110011101 %
b1111101010101011000000001100111111101100100111111011000110100111010101111000011110011101000101100010000000110111011110011001110100110001110100110011111000001101 *
b00000000000000000000000000000000000000000000000000000000000000000000000000000000000000000000000000000000000000000000000000000000000000000000000000000000000000000000000000000000000000000000000100000000000000000000000000000001000000000000000000000000000000000000000000000000000000000000000000000000000000000000000000000000000000000000000000000000000000000000000000000000000000000000000000000000000000000000000000000000000000000000000000000000000000000000000000000000000000000000000000000000000000000000000000000000 0
b00000000000000000000000000000000000000000000000000000000000000000000000000000000000000000000000000000000000000000000000000000000000000000000000000000000000000010000000000000000000000000000000100000000000000000000000000000000000000000000000000000000000000000000000000000000000000000000000000000000000000000000000000000000000000000000000000000000000000000000000000000000000000000000000000000000000000000000000000000000000000000000000000000000000000000000000000000000000000000000000000000000000000000000000000000000 @
b01000100101001111101100100011110 R
b01010101011000000001100111111111 T
b11111011001001111110110001101001 U
b00100110010111011010101011000011 V
b11111010101010110000000011001111 W
b11101100100111111011000110100111 X
b01010111100001111001110100010110 Y
b00100000001101110111100110011101 Z
b00110001110100110011111000001101 [
1\
#301
#302
#303
#304
#305
#306
#307
#308
#309
#310
0\
#311
#312
#313
#314
#315
#316
#317
#318
#319
#320
b00001100 #
b0100010110010110111010001111001100100110010111011010101011000011111111101010101011000000001100111111101100100111111011000110100101010111100001111001110100010110 %
b0010011001011101101010101100001111111010101010110000000011001111111110110010011111101100011010010101011110000111100111010001011000100000001101110111100110011101 *
b00000000000000000000000000000000000000000000000000000000000000000000000000000000000000000000000000000000000000000000000000000000000000000000000000000000000000010000000000000000000000000000000100000000000000000000000000000000000000000000000000000000000000000000000000000000000000000000000000000000000000000000000000000000000000000000000000000000000000000000000000000000000000000000000000000000000000000000000000000000000000000000000000000000000000000000000000000000000000000000000000000000000000000000000000000000 0
b00000000000000000000000000000000000000000000000000000000000000000000000000000000000000000000000000000000000000000000000000000001000000000000000000000000000000010000000000000000000000000000000000000000000000000000000000000000000000000000000000000000000000000000000000000000000000000000000000000000000000000000000000000000000000000000000000000000000000000000000000000000000000000000000000000000000000000000000000000000000000000000000000000000000000000000000000000000000000000000000000000000000000000000000000000000 @
b11111111001001111001110101011001 R
b11001011101101010101100001100100 T
b11111110101010101100000000110011 U
b01000101100101101110100011110011 V
b00100110010111011010101011000011 W
b11111010101010110000000011001111 X
b11111011001001111110110001101001 Y
b01010111100001111001110100010110 Z
b00100000001101110111100110011101 [
1\
#321
#322
#323
#324
#325
#326
#327
#328
#329
#330
0\
#331
#332
#333
#334
#335
#336
#337
#338
#339
